Verilog/mux2/mux81.v
module mux81(y, s2, s1, s0, i0, i1, i2, i3, i4, i5, i6, i7);
				output reg y;
				input s0, s1, s2, i7, i6, i5, i4, i3, i2, i1, i0;
				
				always @ ( * )
					if(!s0 && !s1 && !s2)
						y <= i0;
					else if(!s0 && !s1 && s2)
						y <= i1;
					else if(!s0 && s1 && !s2)
						y <= i2;
					else if(!s0 && s1 && s2)
						y <= i3;
					else if(s0 && !s1 && !s2)
						y <= i4;
					else if(s0 && !s1 && s2)
						y <= i5;
					else if(s0 && s1 && !s2)
						y <= i6;
					else
						y <= i7;
				
endmodule

Verilog/extra/mux/mux81_tb.v
module mux81_tb;
		reg s0, s1, s2, i0, i1, i2, i3, i4, i5, i6, i7;
		wire y;
		
		
		mux81 inst (
				.s0(s0),
				.s1(s1),
				.s2(s2),
				.y(y),
				.i0(i0),
				.i1(i1),
				.i2(i2),
				.i3(i3),
				.i4(i4),
				.i5(i5),
				.i6(i6),
				.i7(i7)
		);
		
		initial begin
		$dumpfile("test_mux81.vcd");
		$dumpvars(0, mux81_tb);
					s0 = 0; s1 = 0; s2 = 0; i0 = 0; i1 = 0; i2 = 0; i3 = 0; i4 = 0; i5 = 0; i6 = 0; i7 = 0;
		#2048	$finish;
		end
		
		always #1 i0 = ~i0;
		always #2 i1 = ~i1;
		always #4 i2 = ~i2;
		always #8 i3 = ~i3;
		always #16 i4= ~i4;
		always #32 i5 = ~i5;
		always #64 i6 = ~i6;
		always #128 i7 = ~i7;
		always #256 s0 = ~s0;
		always #512 s1 = ~s1;
		always #1024 s2 = ~s2;
		
endmodule

Verilog/extra/mux2/test_mux81.vcd
$date
	Tue Nov  8 19:39:39 2022
$end
$version
	Icarus Verilog
$end
$timescale
	1s
$end
$scope module mux81_tb $end
$var wire 1 ! y $end
$var reg 1 " i0 $end
$var reg 1 # i1 $end
$var reg 1 $ i2 $end
$var reg 1 % i3 $end
$var reg 1 & i4 $end
$var reg 1 ' i5 $end
$var reg 1 ( i6 $end
$var reg 1 ) i7 $end
$var reg 1 * s0 $end
$var reg 1 + s1 $end
$var reg 1 , s2 $end
$scope module inst $end
$var wire 1 " i0 $end
$var wire 1 # i1 $end
$var wire 1 $ i2 $end
$var wire 1 % i3 $end
$var wire 1 & i4 $end
$var wire 1 ' i5 $end
$var wire 1 ( i6 $end
$var wire 1 ) i7 $end
$var wire 1 , s0 $end
$var wire 1 + s1 $end
$var wire 1 * s2 $end
$var reg 1 ! y $end
$upscope $end
$upscope $end
$enddefinitions $end
#0
$dumpvars
0,
0+
0*
0)
0(
0'
0&
0%
0$
0#
0"
0!
$end
#1
1!
1"
#2
0!
0"
1#
#3
1!
1"
#4
0!
0"
0#
1$
#5
1!
1"
#6
0!
0"
1#
#7
1!
1"
#8
0!
0"
0#
0$
1%
#9
1!
1"
#10
0!
0"
1#
#11
1!
1"
#12
0!
0"
0#
1$
#13
1!
1"
#14
0!
0"
1#
#15
1!
1"
#16
0!
0"
0#
0$
0%
1&
#17
1!
1"
#18
0!
0"
1#
#19
1!
1"
#20
0!
0"
0#
1$
#21
1!
1"
#22
0!
0"
1#
#23
1!
1"
#24
0!
0"
0#
0$
1%
#25
1!
1"
#26
0!
0"
1#
#27
1!
1"
#28
0!
0"
0#
1$
#29
1!
1"
#30
0!
0"
1#
#31
1!
1"
#32
0!
0"
0#
0$
0%
0&
1'
#33
1!
1"
#34
0!
0"
1#
#35
1!
1"
#36
0!
0"
0#
1$
#37
1!
1"
#38
0!
0"
1#
#39
1!
1"
#40
0!
0"
0#
0$
1%
#41
1!
1"
#42
0!
0"
1#
#43
1!
1"
#44
0!
0"
0#
1$
#45
1!
1"
#46
0!
0"
1#
#47
1!
1"
#48
0!
0"
0#
0$
0%
1&
#49
1!
1"
#50
0!
0"
1#
#51
1!
1"
#52
0!
0"
0#
1$
#53
1!
1"
#54
0!
0"
1#
#55
1!
1"
#56
0!
0"
0#
0$
1%
#57
1!
1"
#58
0!
0"
1#
#59
1!
1"
#60
0!
0"
0#
1$
#61
1!
1"
#62
0!
0"
1#
#63
1!
1"
#64
0!
0"
0#
0$
0%
0&
0'
1(
#65
1!
1"
#66
0!
0"
1#
#67
1!
1"
#68
0!
0"
0#
1$
#69
1!
1"
#70
0!
0"
1#
#71
1!
1"
#72
0!
0"
0#
0$
1%
#73
1!
1"
#74
0!
0"
1#
#75
1!
1"
#76
0!
0"
0#
1$
#77
1!
1"
#78
0!
0"
1#
#79
1!
1"
#80
0!
0"
0#
0$
0%
1&
#81
1!
1"
#82
0!
0"
1#
#83
1!
1"
#84
0!
0"
0#
1$
#85
1!
1"
#86
0!
0"
1#
#87
1!
1"
#88
0!
0"
0#
0$
1%
#89
1!
1"
#90
0!
0"
1#
#91
1!
1"
#92
0!
0"
0#
1$
#93
1!
1"
#94
0!
0"
1#
#95
1!
1"
#96
0!
0"
0#
0$
0%
0&
1'
#97
1!
1"
#98
0!
0"
1#
#99
1!
1"
#100
0!
0"
0#
1$
#101
1!
1"
#102
0!
0"
1#
#103
1!
1"
#104
0!
0"
0#
0$
1%
#105
1!
1"
#106
0!
0"
1#
#107
1!
1"
#108
0!
0"
0#
1$
#109
1!
1"
#110
0!
0"
1#
#111
1!
1"
#112
0!
0"
0#
0$
0%
1&
#113
1!
1"
#114
0!
0"
1#
#115
1!
1"
#116
0!
0"
0#
1$
#117
1!
1"
#118
0!
0"
1#
#119
1!
1"
#120
0!
0"
0#
0$
1%
#121
1!
1"
#122
0!
0"
1#
#123
1!
1"
#124
0!
0"
0#
1$
#125
1!
1"
#126
0!
0"
1#
#127
1!
1"
#128
0!
0"
0#
0$
0%
0&
0'
0(
1)
#129
1!
1"
#130
0!
0"
1#
#131
1!
1"
#132
0!
0"
0#
1$
#133
1!
1"
#134
0!
0"
1#
#135
1!
1"
#136
0!
0"
0#
0$
1%
#137
1!
1"
#138
0!
0"
1#
#139
1!
1"
#140
0!
0"
0#
1$
#141
1!
1"
#142
0!
0"
1#
#143
1!
1"
#144
0!
0"
0#
0$
0%
1&
#145
1!
1"
#146
0!
0"
1#
#147
1!
1"
#148
0!
0"
0#
1$
#149
1!
1"
#150
0!
0"
1#
#151
1!
1"
#152
0!
0"
0#
0$
1%
#153
1!
1"
#154
0!
0"
1#
#155
1!
1"
#156
0!
0"
0#
1$
#157
1!
1"
#158
0!
0"
1#
#159
1!
1"
#160
0!
0"
0#
0$
0%
0&
1'
#161
1!
1"
#162
0!
0"
1#
#163
1!
1"
#164
0!
0"
0#
1$
#165
1!
1"
#166
0!
0"
1#
#167
1!
1"
#168
0!
0"
0#
0$
1%
#169
1!
1"
#170
0!
0"
1#
#171
1!
1"
#172
0!
0"
0#
1$
#173
1!
1"
#174
0!
0"
1#
#175
1!
1"
#176
0!
0"
0#
0$
0%
1&
#177
1!
1"
#178
0!
0"
1#
#179
1!
1"
#180
0!
0"
0#
1$
#181
1!
1"
#182
0!
0"
1#
#183
1!
1"
#184
0!
0"
0#
0$
1%
#185
1!
1"
#186
0!
0"
1#
#187
1!
1"
#188
0!
0"
0#
1$
#189
1!
1"
#190
0!
0"
1#
#191
1!
1"
#192
0!
0"
0#
0$
0%
0&
0'
1(
#193
1!
1"
#194
0!
0"
1#
#195
1!
1"
#196
0!
0"
0#
1$
#197
1!
1"
#198
0!
0"
1#
#199
1!
1"
#200
0!
0"
0#
0$
1%
#201
1!
1"
#202
0!
0"
1#
#203
1!
1"
#204
0!
0"
0#
1$
#205
1!
1"
#206
0!
0"
1#
#207
1!
1"
#208
0!
0"
0#
0$
0%
1&
#209
1!
1"
#210
0!
0"
1#
#211
1!
1"
#212
0!
0"
0#
1$
#213
1!
1"
#214
0!
0"
1#
#215
1!
1"
#216
0!
0"
0#
0$
1%
#217
1!
1"
#218
0!
0"
1#
#219
1!
1"
#220
0!
0"
0#
1$
#221
1!
1"
#222
0!
0"
1#
#223
1!
1"
#224
0!
0"
0#
0$
0%
0&
1'
#225
1!
1"
#226
0!
0"
1#
#227
1!
1"
#228
0!
0"
0#
1$
#229
1!
1"
#230
0!
0"
1#
#231
1!
1"
#232
0!
0"
0#
0$
1%
#233
1!
1"
#234
0!
0"
1#
#235
1!
1"
#236
0!
0"
0#
1$
#237
1!
1"
#238
0!
0"
1#
#239
1!
1"
#240
0!
0"
0#
0$
0%
1&
#241
1!
1"
#242
0!
0"
1#
#243
1!
1"
#244
0!
0"
0#
1$
#245
1!
1"
#246
0!
0"
1#
#247
1!
1"
#248
0!
0"
0#
0$
1%
#249
1!
1"
#250
0!
0"
1#
#251
1!
1"
#252
0!
0"
0#
1$
#253
1!
1"
#254
0!
0"
1#
#255
1!
1"
#256
0!
0"
0#
0$
0%
0&
0'
0(
0)
1*
#257
1"
#258
1!
0"
1#
#259
1"
#260
0!
0"
0#
1$
#261
1"
#262
1!
0"
1#
#263
1"
#264
0!
0"
0#
0$
1%
#265
1"
#266
1!
0"
1#
#267
1"
#268
0!
0"
0#
1$
#269
1"
#270
1!
0"
1#
#271
1"
#272
0!
0"
0#
0$
0%
1&
#273
1"
#274
1!
0"
1#
#275
1"
#276
0!
0"
0#
1$
#277
1"
#278
1!
0"
1#
#279
1"
#280
0!
0"
0#
0$
1%
#281
1"
#282
1!
0"
1#
#283
1"
#284
0!
0"
0#
1$
#285
1"
#286
1!
0"
1#
#287
1"
#288
0!
0"
0#
0$
0%
0&
1'
#289
1"
#290
1!
0"
1#
#291
1"
#292
0!
0"
0#
1$
#293
1"
#294
1!
0"
1#
#295
1"
#296
0!
0"
0#
0$
1%
#297
1"
#298
1!
0"
1#
#299
1"
#300
0!
0"
0#
1$
#301
1"
#302
1!
0"
1#
#303
1"
#304
0!
0"
0#
0$
0%
1&
#305
1"
#306
1!
0"
1#
#307
1"
#308
0!
0"
0#
1$
#309
1"
#310
1!
0"
1#
#311
1"
#312
0!
0"
0#
0$
1%
#313
1"
#314
1!
0"
1#
#315
1"
#316
0!
0"
0#
1$
#317
1"
#318
1!
0"
1#
#319
1"
#320
0!
0"
0#
0$
0%
0&
0'
1(
#321
1"
#322
1!
0"
1#
#323
1"
#324
0!
0"
0#
1$
#325
1"
#326
1!
0"
1#
#327
1"
#328
0!
0"
0#
0$
1%
#329
1"
#330
1!
0"
1#
#331
1"
#332
0!
0"
0#
1$
#333
1"
#334
1!
0"
1#
#335
1"
#336
0!
0"
0#
0$
0%
1&
#337
1"
#338
1!
0"
1#
#339
1"
#340
0!
0"
0#
1$
#341
1"
#342
1!
0"
1#
#343
1"
#344
0!
0"
0#
0$
1%
#345
1"
#346
1!
0"
1#
#347
1"
#348
0!
0"
0#
1$
#349
1"
#350
1!
0"
1#
#351
1"
#352
0!
0"
0#
0$
0%
0&
1'
#353
1"
#354
1!
0"
1#
#355
1"
#356
0!
0"
0#
1$
#357
1"
#358
1!
0"
1#
#359
1"
#360
0!
0"
0#
0$
1%
#361
1"
#362
1!
0"
1#
#363
1"
#364
0!
0"
0#
1$
#365
1"
#366
1!
0"
1#
#367
1"
#368
0!
0"
0#
0$
0%
1&
#369
1"
#370
1!
0"
1#
#371
1"
#372
0!
0"
0#
1$
#373
1"
#374
1!
0"
1#
#375
1"
#376
0!
0"
0#
0$
1%
#377
1"
#378
1!
0"
1#
#379
1"
#380
0!
0"
0#
1$
#381
1"
#382
1!
0"
1#
#383
1"
#384
0!
0"
0#
0$
0%
0&
0'
0(
1)
#385
1"
#386
1!
0"
1#
#387
1"
#388
0!
0"
0#
1$
#389
1"
#390
1!
0"
1#
#391
1"
#392
0!
0"
0#
0$
1%
#393
1"
#394
1!
0"
1#
#395
1"
#396
0!
0"
0#
1$
#397
1"
#398
1!
0"
1#
#399
1"
#400
0!
0"
0#
0$
0%
1&
#401
1"
#402
1!
0"
1#
#403
1"
#404
0!
0"
0#
1$
#405
1"
#406
1!
0"
1#
#407
1"
#408
0!
0"
0#
0$
1%
#409
1"
#410
1!
0"
1#
#411
1"
#412
0!
0"
0#
1$
#413
1"
#414
1!
0"
1#
#415
1"
#416
0!
0"
0#
0$
0%
0&
1'
#417
1"
#418
1!
0"
1#
#419
1"
#420
0!
0"
0#
1$
#421
1"
#422
1!
0"
1#
#423
1"
#424
0!
0"
0#
0$
1%
#425
1"
#426
1!
0"
1#
#427
1"
#428
0!
0"
0#
1$
#429
1"
#430
1!
0"
1#
#431
1"
#432
0!
0"
0#
0$
0%
1&
#433
1"
#434
1!
0"
1#
#435
1"
#436
0!
0"
0#
1$
#437
1"
#438
1!
0"
1#
#439
1"
#440
0!
0"
0#
0$
1%
#441
1"
#442
1!
0"
1#
#443
1"
#444
0!
0"
0#
1$
#445
1"
#446
1!
0"
1#
#447
1"
#448
0!
0"
0#
0$
0%
0&
0'
1(
#449
1"
#450
1!
0"
1#
#451
1"
#452
0!
0"
0#
1$
#453
1"
#454
1!
0"
1#
#455
1"
#456
0!
0"
0#
0$
1%
#457
1"
#458
1!
0"
1#
#459
1"
#460
0!
0"
0#
1$
#461
1"
#462
1!
0"
1#
#463
1"
#464
0!
0"
0#
0$
0%
1&
#465
1"
#466
1!
0"
1#
#467
1"
#468
0!
0"
0#
1$
#469
1"
#470
1!
0"
1#
#471
1"
#472
0!
0"
0#
0$
1%
#473
1"
#474
1!
0"
1#
#475
1"
#476
0!
0"
0#
1$
#477
1"
#478
1!
0"
1#
#479
1"
#480
0!
0"
0#
0$
0%
0&
1'
#481
1"
#482
1!
0"
1#
#483
1"
#484
0!
0"
0#
1$
#485
1"
#486
1!
0"
1#
#487
1"
#488
0!
0"
0#
0$
1%
#489
1"
#490
1!
0"
1#
#491
1"
#492
0!
0"
0#
1$
#493
1"
#494
1!
0"
1#
#495
1"
#496
0!
0"
0#
0$
0%
1&
#497
1"
#498
1!
0"
1#
#499
1"
#500
0!
0"
0#
1$
#501
1"
#502
1!
0"
1#
#503
1"
#504
0!
0"
0#
0$
1%
#505
1"
#506
1!
0"
1#
#507
1"
#508
0!
0"
0#
1$
#509
1"
#510
1!
0"
1#
#511
1"
#512
0!
0"
0#
0$
0%
0&
0'
0(
0)
0*
1+
#513
1"
#514
0"
1#
#515
1"
#516
1!
0"
0#
1$
#517
1"
#518
0"
1#
#519
1"
#520
0!
0"
0#
0$
1%
#521
1"
#522
0"
1#
#523
1"
#524
1!
0"
0#
1$
#525
1"
#526
0"
1#
#527
1"
#528
0!
0"
0#
0$
0%
1&
#529
1"
#530
0"
1#
#531
1"
#532
1!
0"
0#
1$
#533
1"
#534
0"
1#
#535
1"
#536
0!
0"
0#
0$
1%
#537
1"
#538
0"
1#
#539
1"
#540
1!
0"
0#
1$
#541
1"
#542
0"
1#
#543
1"
#544
0!
0"
0#
0$
0%
0&
1'
#545
1"
#546
0"
1#
#547
1"
#548
1!
0"
0#
1$
#549
1"
#550
0"
1#
#551
1"
#552
0!
0"
0#
0$
1%
#553
1"
#554
0"
1#
#555
1"
#556
1!
0"
0#
1$
#557
1"
#558
0"
1#
#559
1"
#560
0!
0"
0#
0$
0%
1&
#561
1"
#562
0"
1#
#563
1"
#564
1!
0"
0#
1$
#565
1"
#566
0"
1#
#567
1"
#568
0!
0"
0#
0$
1%
#569
1"
#570
0"
1#
#571
1"
#572
1!
0"
0#
1$
#573
1"
#574
0"
1#
#575
1"
#576
0!
0"
0#
0$
0%
0&
0'
1(
#577
1"
#578
0"
1#
#579
1"
#580
1!
0"
0#
1$
#581
1"
#582
0"
1#
#583
1"
#584
0!
0"
0#
0$
1%
#585
1"
#586
0"
1#
#587
1"
#588
1!
0"
0#
1$
#589
1"
#590
0"
1#
#591
1"
#592
0!
0"
0#
0$
0%
1&
#593
1"
#594
0"
1#
#595
1"
#596
1!
0"
0#
1$
#597
1"
#598
0"
1#
#599
1"
#600
0!
0"
0#
0$
1%
#601
1"
#602
0"
1#
#603
1"
#604
1!
0"
0#
1$
#605
1"
#606
0"
1#
#607
1"
#608
0!
0"
0#
0$
0%
0&
1'
#609
1"
#610
0"
1#
#611
1"
#612
1!
0"
0#
1$
#613
1"
#614
0"
1#
#615
1"
#616
0!
0"
0#
0$
1%
#617
1"
#618
0"
1#
#619
1"
#620
1!
0"
0#
1$
#621
1"
#622
0"
1#
#623
1"
#624
0!
0"
0#
0$
0%
1&
#625
1"
#626
0"
1#
#627
1"
#628
1!
0"
0#
1$
#629
1"
#630
0"
1#
#631
1"
#632
0!
0"
0#
0$
1%
#633
1"
#634
0"
1#
#635
1"
#636
1!
0"
0#
1$
#637
1"
#638
0"
1#
#639
1"
#640
0!
0"
0#
0$
0%
0&
0'
0(
1)
#641
1"
#642
0"
1#
#643
1"
#644
1!
0"
0#
1$
#645
1"
#646
0"
1#
#647
1"
#648
0!
0"
0#
0$
1%
#649
1"
#650
0"
1#
#651
1"
#652
1!
0"
0#
1$
#653
1"
#654
0"
1#
#655
1"
#656
0!
0"
0#
0$
0%
1&
#657
1"
#658
0"
1#
#659
1"
#660
1!
0"
0#
1$
#661
1"
#662
0"
1#
#663
1"
#664
0!
0"
0#
0$
1%
#665
1"
#666
0"
1#
#667
1"
#668
1!
0"
0#
1$
#669
1"
#670
0"
1#
#671
1"
#672
0!
0"
0#
0$
0%
0&
1'
#673
1"
#674
0"
1#
#675
1"
#676
1!
0"
0#
1$
#677
1"
#678
0"
1#
#679
1"
#680
0!
0"
0#
0$
1%
#681
1"
#682
0"
1#
#683
1"
#684
1!
0"
0#
1$
#685
1"
#686
0"
1#
#687
1"
#688
0!
0"
0#
0$
0%
1&
#689
1"
#690
0"
1#
#691
1"
#692
1!
0"
0#
1$
#693
1"
#694
0"
1#
#695
1"
#696
0!
0"
0#
0$
1%
#697
1"
#698
0"
1#
#699
1"
#700
1!
0"
0#
1$
#701
1"
#702
0"
1#
#703
1"
#704
0!
0"
0#
0$
0%
0&
0'
1(
#705
1"
#706
0"
1#
#707
1"
#708
1!
0"
0#
1$
#709
1"
#710
0"
1#
#711
1"
#712
0!
0"
0#
0$
1%
#713
1"
#714
0"
1#
#715
1"
#716
1!
0"
0#
1$
#717
1"
#718
0"
1#
#719
1"
#720
0!
0"
0#
0$
0%
1&
#721
1"
#722
0"
1#
#723
1"
#724
1!
0"
0#
1$
#725
1"
#726
0"
1#
#727
1"
#728
0!
0"
0#
0$
1%
#729
1"
#730
0"
1#
#731
1"
#732
1!
0"
0#
1$
#733
1"
#734
0"
1#
#735
1"
#736
0!
0"
0#
0$
0%
0&
1'
#737
1"
#738
0"
1#
#739
1"
#740
1!
0"
0#
1$
#741
1"
#742
0"
1#
#743
1"
#744
0!
0"
0#
0$
1%
#745
1"
#746
0"
1#
#747
1"
#748
1!
0"
0#
1$
#749
1"
#750
0"
1#
#751
1"
#752
0!
0"
0#
0$
0%
1&
#753
1"
#754
0"
1#
#755
1"
#756
1!
0"
0#
1$
#757
1"
#758
0"
1#
#759
1"
#760
0!
0"
0#
0$
1%
#761
1"
#762
0"
1#
#763
1"
#764
1!
0"
0#
1$
#765
1"
#766
0"
1#
#767
1"
#768
0!
0"
0#
0$
0%
0&
0'
0(
0)
1*
#769
1"
#770
0"
1#
#771
1"
#772
0"
0#
1$
#773
1"
#774
0"
1#
#775
1"
#776
1!
0"
0#
0$
1%
#777
1"
#778
0"
1#
#779
1"
#780
0"
0#
1$
#781
1"
#782
0"
1#
#783
1"
#784
0!
0"
0#
0$
0%
1&
#785
1"
#786
0"
1#
#787
1"
#788
0"
0#
1$
#789
1"
#790
0"
1#
#791
1"
#792
1!
0"
0#
0$
1%
#793
1"
#794
0"
1#
#795
1"
#796
0"
0#
1$
#797
1"
#798
0"
1#
#799
1"
#800
0!
0"
0#
0$
0%
0&
1'
#801
1"
#802
0"
1#
#803
1"
#804
0"
0#
1$
#805
1"
#806
0"
1#
#807
1"
#808
1!
0"
0#
0$
1%
#809
1"
#810
0"
1#
#811
1"
#812
0"
0#
1$
#813
1"
#814
0"
1#
#815
1"
#816
0!
0"
0#
0$
0%
1&
#817
1"
#818
0"
1#
#819
1"
#820
0"
0#
1$
#821
1"
#822
0"
1#
#823
1"
#824
1!
0"
0#
0$
1%
#825
1"
#826
0"
1#
#827
1"
#828
0"
0#
1$
#829
1"
#830
0"
1#
#831
1"
#832
0!
0"
0#
0$
0%
0&
0'
1(
#833
1"
#834
0"
1#
#835
1"
#836
0"
0#
1$
#837
1"
#838
0"
1#
#839
1"
#840
1!
0"
0#
0$
1%
#841
1"
#842
0"
1#
#843
1"
#844
0"
0#
1$
#845
1"
#846
0"
1#
#847
1"
#848
0!
0"
0#
0$
0%
1&
#849
1"
#850
0"
1#
#851
1"
#852
0"
0#
1$
#853
1"
#854
0"
1#
#855
1"
#856
1!
0"
0#
0$
1%
#857
1"
#858
0"
1#
#859
1"
#860
0"
0#
1$
#861
1"
#862
0"
1#
#863
1"
#864
0!
0"
0#
0$
0%
0&
1'
#865
1"
#866
0"
1#
#867
1"
#868
0"
0#
1$
#869
1"
#870
0"
1#
#871
1"
#872
1!
0"
0#
0$
1%
#873
1"
#874
0"
1#
#875
1"
#876
0"
0#
1$
#877
1"
#878
0"
1#
#879
1"
#880
0!
0"
0#
0$
0%
1&
#881
1"
#882
0"
1#
#883
1"
#884
0"
0#
1$
#885
1"
#886
0"
1#
#887
1"
#888
1!
0"
0#
0$
1%
#889
1"
#890
0"
1#
#891
1"
#892
0"
0#
1$
#893
1"
#894
0"
1#
#895
1"
#896
0!
0"
0#
0$
0%
0&
0'
0(
1)
#897
1"
#898
0"
1#
#899
1"
#900
0"
0#
1$
#901
1"
#902
0"
1#
#903
1"
#904
1!
0"
0#
0$
1%
#905
1"
#906
0"
1#
#907
1"
#908
0"
0#
1$
#909
1"
#910
0"
1#
#911
1"
#912
0!
0"
0#
0$
0%
1&
#913
1"
#914
0"
1#
#915
1"
#916
0"
0#
1$
#917
1"
#918
0"
1#
#919
1"
#920
1!
0"
0#
0$
1%
#921
1"
#922
0"
1#
#923
1"
#924
0"
0#
1$
#925
1"
#926
0"
1#
#927
1"
#928
0!
0"
0#
0$
0%
0&
1'
#929
1"
#930
0"
1#
#931
1"
#932
0"
0#
1$
#933
1"
#934
0"
1#
#935
1"
#936
1!
0"
0#
0$
1%
#937
1"
#938
0"
1#
#939
1"
#940
0"
0#
1$
#941
1"
#942
0"
1#
#943
1"
#944
0!
0"
0#
0$
0%
1&
#945
1"
#946
0"
1#
#947
1"
#948
0"
0#
1$
#949
1"
#950
0"
1#
#951
1"
#952
1!
0"
0#
0$
1%
#953
1"
#954
0"
1#
#955
1"
#956
0"
0#
1$
#957
1"
#958
0"
1#
#959
1"
#960
0!
0"
0#
0$
0%
0&
0'
1(
#961
1"
#962
0"
1#
#963
1"
#964
0"
0#
1$
#965
1"
#966
0"
1#
#967
1"
#968
1!
0"
0#
0$
1%
#969
1"
#970
0"
1#
#971
1"
#972
0"
0#
1$
#973
1"
#974
0"
1#
#975
1"
#976
0!
0"
0#
0$
0%
1&
#977
1"
#978
0"
1#
#979
1"
#980
0"
0#
1$
#981
1"
#982
0"
1#
#983
1"
#984
1!
0"
0#
0$
1%
#985
1"
#986
0"
1#
#987
1"
#988
0"
0#
1$
#989
1"
#990
0"
1#
#991
1"
#992
0!
0"
0#
0$
0%
0&
1'
#993
1"
#994
0"
1#
#995
1"
#996
0"
0#
1$
#997
1"
#998
0"
1#
#999
1"
#1000
1!
0"
0#
0$
1%
#1001
1"
#1002
0"
1#
#1003
1"
#1004
0"
0#
1$
#1005
1"
#1006
0"
1#
#1007
1"
#1008
0!
0"
0#
0$
0%
1&
#1009
1"
#1010
0"
1#
#1011
1"
#1012
0"
0#
1$
#1013
1"
#1014
0"
1#
#1015
1"
#1016
1!
0"
0#
0$
1%
#1017
1"
#1018
0"
1#
#1019
1"
#1020
0"
0#
1$
#1021
1"
#1022
0"
1#
#1023
1"
#1024
0!
0"
0#
0$
0%
0&
0'
0(
0)
0*
0+
1,
#1025
1"
#1026
0"
1#
#1027
1"
#1028
0"
0#
1$
#1029
1"
#1030
0"
1#
#1031
1"
#1032
0"
0#
0$
1%
#1033
1"
#1034
0"
1#
#1035
1"
#1036
0"
0#
1$
#1037
1"
#1038
0"
1#
#1039
1"
#1040
1!
0"
0#
0$
0%
1&
#1041
1"
#1042
0"
1#
#1043
1"
#1044
0"
0#
1$
#1045
1"
#1046
0"
1#
#1047
1"
#1048
0"
0#
0$
1%
#1049
1"
#1050
0"
1#
#1051
1"
#1052
0"
0#
1$
#1053
1"
#1054
0"
1#
#1055
1"
#1056
0!
0"
0#
0$
0%
0&
1'
#1057
1"
#1058
0"
1#
#1059
1"
#1060
0"
0#
1$
#1061
1"
#1062
0"
1#
#1063
1"
#1064
0"
0#
0$
1%
#1065
1"
#1066
0"
1#
#1067
1"
#1068
0"
0#
1$
#1069
1"
#1070
0"
1#
#1071
1"
#1072
1!
0"
0#
0$
0%
1&
#1073
1"
#1074
0"
1#
#1075
1"
#1076
0"
0#
1$
#1077
1"
#1078
0"
1#
#1079
1"
#1080
0"
0#
0$
1%
#1081
1"
#1082
0"
1#
#1083
1"
#1084
0"
0#
1$
#1085
1"
#1086
0"
1#
#1087
1"
#1088
0!
0"
0#
0$
0%
0&
0'
1(
#1089
1"
#1090
0"
1#
#1091
1"
#1092
0"
0#
1$
#1093
1"
#1094
0"
1#
#1095
1"
#1096
0"
0#
0$
1%
#1097
1"
#1098
0"
1#
#1099
1"
#1100
0"
0#
1$
#1101
1"
#1102
0"
1#
#1103
1"
#1104
1!
0"
0#
0$
0%
1&
#1105
1"
#1106
0"
1#
#1107
1"
#1108
0"
0#
1$
#1109
1"
#1110
0"
1#
#1111
1"
#1112
0"
0#
0$
1%
#1113
1"
#1114
0"
1#
#1115
1"
#1116
0"
0#
1$
#1117
1"
#1118
0"
1#
#1119
1"
#1120
0!
0"
0#
0$
0%
0&
1'
#1121
1"
#1122
0"
1#
#1123
1"
#1124
0"
0#
1$
#1125
1"
#1126
0"
1#
#1127
1"
#1128
0"
0#
0$
1%
#1129
1"
#1130
0"
1#
#1131
1"
#1132
0"
0#
1$
#1133
1"
#1134
0"
1#
#1135
1"
#1136
1!
0"
0#
0$
0%
1&
#1137
1"
#1138
0"
1#
#1139
1"
#1140
0"
0#
1$
#1141
1"
#1142
0"
1#
#1143
1"
#1144
0"
0#
0$
1%
#1145
1"
#1146
0"
1#
#1147
1"
#1148
0"
0#
1$
#1149
1"
#1150
0"
1#
#1151
1"
#1152
0!
0"
0#
0$
0%
0&
0'
0(
1)
#1153
1"
#1154
0"
1#
#1155
1"
#1156
0"
0#
1$
#1157
1"
#1158
0"
1#
#1159
1"
#1160
0"
0#
0$
1%
#1161
1"
#1162
0"
1#
#1163
1"
#1164
0"
0#
1$
#1165
1"
#1166
0"
1#
#1167
1"
#1168
1!
0"
0#
0$
0%
1&
#1169
1"
#1170
0"
1#
#1171
1"
#1172
0"
0#
1$
#1173
1"
#1174
0"
1#
#1175
1"
#1176
0"
0#
0$
1%
#1177
1"
#1178
0"
1#
#1179
1"
#1180
0"
0#
1$
#1181
1"
#1182
0"
1#
#1183
1"
#1184
0!
0"
0#
0$
0%
0&
1'
#1185
1"
#1186
0"
1#
#1187
1"
#1188
0"
0#
1$
#1189
1"
#1190
0"
1#
#1191
1"
#1192
0"
0#
0$
1%
#1193
1"
#1194
0"
1#
#1195
1"
#1196
0"
0#
1$
#1197
1"
#1198
0"
1#
#1199
1"
#1200
1!
0"
0#
0$
0%
1&
#1201
1"
#1202
0"
1#
#1203
1"
#1204
0"
0#
1$
#1205
1"
#1206
0"
1#
#1207
1"
#1208
0"
0#
0$
1%
#1209
1"
#1210
0"
1#
#1211
1"
#1212
0"
0#
1$
#1213
1"
#1214
0"
1#
#1215
1"
#1216
0!
0"
0#
0$
0%
0&
0'
1(
#1217
1"
#1218
0"
1#
#1219
1"
#1220
0"
0#
1$
#1221
1"
#1222
0"
1#
#1223
1"
#1224
0"
0#
0$
1%
#1225
1"
#1226
0"
1#
#1227
1"
#1228
0"
0#
1$
#1229
1"
#1230
0"
1#
#1231
1"
#1232
1!
0"
0#
0$
0%
1&
#1233
1"
#1234
0"
1#
#1235
1"
#1236
0"
0#
1$
#1237
1"
#1238
0"
1#
#1239
1"
#1240
0"
0#
0$
1%
#1241
1"
#1242
0"
1#
#1243
1"
#1244
0"
0#
1$
#1245
1"
#1246
0"
1#
#1247
1"
#1248
0!
0"
0#
0$
0%
0&
1'
#1249
1"
#1250
0"
1#
#1251
1"
#1252
0"
0#
1$
#1253
1"
#1254
0"
1#
#1255
1"
#1256
0"
0#
0$
1%
#1257
1"
#1258
0"
1#
#1259
1"
#1260
0"
0#
1$
#1261
1"
#1262
0"
1#
#1263
1"
#1264
1!
0"
0#
0$
0%
1&
#1265
1"
#1266
0"
1#
#1267
1"
#1268
0"
0#
1$
#1269
1"
#1270
0"
1#
#1271
1"
#1272
0"
0#
0$
1%
#1273
1"
#1274
0"
1#
#1275
1"
#1276
0"
0#
1$
#1277
1"
#1278
0"
1#
#1279
1"
#1280
0!
0"
0#
0$
0%
0&
0'
0(
0)
1*
#1281
1"
#1282
0"
1#
#1283
1"
#1284
0"
0#
1$
#1285
1"
#1286
0"
1#
#1287
1"
#1288
0"
0#
0$
1%
#1289
1"
#1290
0"
1#
#1291
1"
#1292
0"
0#
1$
#1293
1"
#1294
0"
1#
#1295
1"
#1296
0"
0#
0$
0%
1&
#1297
1"
#1298
0"
1#
#1299
1"
#1300
0"
0#
1$
#1301
1"
#1302
0"
1#
#1303
1"
#1304
0"
0#
0$
1%
#1305
1"
#1306
0"
1#
#1307
1"
#1308
0"
0#
1$
#1309
1"
#1310
0"
1#
#1311
1"
#1312
1!
0"
0#
0$
0%
0&
1'
#1313
1"
#1314
0"
1#
#1315
1"
#1316
0"
0#
1$
#1317
1"
#1318
0"
1#
#1319
1"
