Verilog/example/left_shift_register/lsr.v
module lsr(out, d, clk, rst);
	parameter N = 4;
	input d, clk, rst;
	output reg[N-1:0] out;
	
	always @ (posedge clk)
		begin
			if(~rst)
				out <= 0;
			else
				out <= {out[2:0], d};
		end

endmodule

Verilog/example/left_shift_register/lsr_tb.v
module lsr_tb;
	parameter N = 4;
	wire[N-1:0]  out;
	reg d, clk, rst;
	
	lsr uut(
		.out(out),
		.d(d),
		.clk(clk),
		.rst(rst)
	);
	
	initial begin
	$dumpfile("dump.vcd");
	$dumpvars(0, lsr_tb);
		{d, clk, rst} <= 0;
	#200 $finish;
	end
	
	always #10 clk = ~clk;
	always #10 d = d + 1;

endmodule

Verilog/HDL/left_shift_register/dump.vcd
$date
	Tue Feb 21 12:13:33 2023
$end
$version
	Icarus Verilog
$end
$timescale
	1s
$end
$scope module lsr_tb $end
$var wire 4 ! out [3:0] $end
$var reg 1 " clk $end
$var reg 1 # d $end
$var reg 1 $ rst $end
$scope module uut $end
$var wire 1 " clk $end
$var wire 1 # d $end
$var wire 1 $ rst $end
$var reg 4 % out [3:0] $end
$upscope $end
$upscope $end
$enddefinitions $end
#0
$dumpvars
bx %
0$
0#
0"
bx !
$end
#10
b0 !
b0 %
1#
1"
#20
0#
0"
#30
1#
1"
#40
0#
0"
#50
1#
1"
#60
0#
0"
#70
1#
1"
#80
0#
0"
#90
1#
1"
#100
0#
0"
#110
1#
1"
#120
0#
0"
#130
1#
1"
#140
0#
0"
#150
1#
1"
#160
0#
0"
#170
1#
1"
#180
0#
0"
#190
1#
1"
#200
0#
0"
