Verilog/extra/mux3/mux81.v
module mux81(output reg y, input [0:7] i, input[2:0] s);
				
				always @ ( * )
					if(!s[2] && !s[1] && !s[0])
						y <= i[0];
					else if(!s[2] && !s[1] && s[0])
						y <= i[1];
					else if(!s[2] && s[1] && !s[0])
						y <= i[2];
					else if(!s[2] && s[1] && s[0])
						y <= i[3];
					else if(s[2] && !s[1] && !s[0])
						y <= i[4];
					else if(s[2] && !s[1] && s[0])
						y <= i[5];
					else if(s[2] && s[1] && !s[0])
						y <= i[6];
					else
						y <= i[7];
				
endmodule

Verilog/mux3/mux81_tb.v
module mux81_tb;
		reg [0:7] i;
		reg [2:0] s;
		wire y;
		
		
		mux81 inst (
				.y(y),
				.i(i),
				.s(s)
		);
		
		initial begin
		$dumpfile("test_mux81.vcd");
		$dumpvars(0, mux81_tb);
					s[0] = 0; s[1] = 0; s[2] = 0; i[0] = 0; i[1] = 0; i[2] = 0; i[3] = 0; i[4] = 0; i[5] = 0; i[6] = 0; i[7] = 0;
		#2048	$finish;
		end
		
//		genvar idx;
//		integer tm = 2;
//		for(idx = 0; idx < 10; idx = idx + 1) begin
//			always #tm i[idx] = ~i[idx];
//			assign tm = tm * 2;
//		end
		
		always #1 i[0] = ~i[0];
		always #2 i[1] = ~i[1];
		always #4 i[2] = ~i[2];
		always #8 i[3] = ~i[3];
		always #16 i[4]= ~i[4];
		always #32 i[5] = ~i[5];
		always #64 i[6] = ~i[6];
		always #128 i[7] = ~i[7];
		always #256 s[0] = ~s[0];
		always #512 s[1] = ~s[1];
		always #1024 s[2] = ~s[2];
		
endmodule

Verilog/extra/mux3/test_mux81.vcd
$date
	Tue Nov  8 21:13:22 2022
$end
$version
	Icarus Verilog
$end
$timescale
	1s
$end
$scope module mux81_tb $end
$var wire 1 ! y $end
$var reg 8 " i [0:7] $end
$var reg 3 # s [2:0] $end
$scope module inst $end
$var wire 8 $ i [0:7] $end
$var wire 3 % s [2:0] $end
$var reg 1 ! y $end
$upscope $end
$upscope $end
$enddefinitions $end
#0
$dumpvars
b0 %
b0 $
b0 #
b0 "
0!
$end
#1
1!
b10000000 "
b10000000 $
#2
0!
b1000000 "
b1000000 $
#3
1!
b11000000 "
b11000000 $
#4
0!
b100000 "
b100000 $
#5
1!
b10100000 "
b10100000 $
#6
0!
b1100000 "
b1100000 $
#7
1!
b11100000 "
b11100000 $
#8
0!
b10000 "
b10000 $
#9
1!
b10010000 "
b10010000 $
#10
0!
b1010000 "
b1010000 $
#11
1!
b11010000 "
b11010000 $
#12
0!
b110000 "
b110000 $
#13
1!
b10110000 "
b10110000 $
#14
0!
b1110000 "
b1110000 $
#15
1!
b11110000 "
b11110000 $
#16
0!
b1000 "
b1000 $
#17
1!
b10001000 "
b10001000 $
#18
0!
b1001000 "
b1001000 $
#19
1!
b11001000 "
b11001000 $
#20
0!
b101000 "
b101000 $
#21
1!
b10101000 "
b10101000 $
#22
0!
b1101000 "
b1101000 $
#23
1!
b11101000 "
b11101000 $
#24
0!
b11000 "
b11000 $
#25
1!
b10011000 "
b10011000 $
#26
0!
b1011000 "
b1011000 $
#27
1!
b11011000 "
b11011000 $
#28
0!
b111000 "
b111000 $
#29
1!
b10111000 "
b10111000 $
#30
0!
b1111000 "
b1111000 $
#31
1!
b11111000 "
b11111000 $
#32
0!
b100 "
b100 $
#33
1!
b10000100 "
b10000100 $
#34
0!
b1000100 "
b1000100 $
#35
1!
b11000100 "
b11000100 $
#36
0!
b100100 "
b100100 $
#37
1!
b10100100 "
b10100100 $
#38
0!
b1100100 "
b1100100 $
#39
1!
b11100100 "
b11100100 $
#40
0!
b10100 "
b10100 $
#41
1!
b10010100 "
b10010100 $
#42
0!
b1010100 "
b1010100 $
#43
1!
b11010100 "
b11010100 $
#44
0!
b110100 "
b110100 $
#45
1!
b10110100 "
b10110100 $
#46
0!
b1110100 "
b1110100 $
#47
1!
b11110100 "
b11110100 $
#48
0!
b1100 "
b1100 $
#49
1!
b10001100 "
b10001100 $
#50
0!
b1001100 "
b1001100 $
#51
1!
b11001100 "
b11001100 $
#52
0!
b101100 "
b101100 $
#53
1!
b10101100 "
b10101100 $
#54
0!
b1101100 "
b1101100 $
#55
1!
b11101100 "
b11101100 $
#56
0!
b11100 "
b11100 $
#57
1!
b10011100 "
b10011100 $
#58
0!
b1011100 "
b1011100 $
#59
1!
b11011100 "
b11011100 $
#60
0!
b111100 "
b111100 $
#61
1!
b10111100 "
b10111100 $
#62
0!
b1111100 "
b1111100 $
#63
1!
b11111100 "
b11111100 $
#64
0!
b10 "
b10 $
#65
1!
b10000010 "
b10000010 $
#66
0!
b1000010 "
b1000010 $
#67
1!
b11000010 "
b11000010 $
#68
0!
b100010 "
b100010 $
#69
1!
b10100010 "
b10100010 $
#70
0!
b1100010 "
b1100010 $
#71
1!
b11100010 "
b11100010 $
#72
0!
b10010 "
b10010 $
#73
1!
b10010010 "
b10010010 $
#74
0!
b1010010 "
b1010010 $
#75
1!
b11010010 "
b11010010 $
#76
0!
b110010 "
b110010 $
#77
1!
b10110010 "
b10110010 $
#78
0!
b1110010 "
b1110010 $
#79
1!
b11110010 "
b11110010 $
#80
0!
b1010 "
b1010 $
#81
1!
b10001010 "
b10001010 $
#82
0!
b1001010 "
b1001010 $
#83
1!
b11001010 "
b11001010 $
#84
0!
b101010 "
b101010 $
#85
1!
b10101010 "
b10101010 $
#86
0!
b1101010 "
b1101010 $
#87
1!
b11101010 "
b11101010 $
#88
0!
b11010 "
b11010 $
#89
1!
b10011010 "
b10011010 $
#90
0!
b1011010 "
b1011010 $
#91
1!
b11011010 "
b11011010 $
#92
0!
b111010 "
b111010 $
#93
1!
b10111010 "
b10111010 $
#94
0!
b1111010 "
b1111010 $
#95
1!
b11111010 "
b11111010 $
#96
0!
b110 "
b110 $
#97
1!
b10000110 "
b10000110 $
#98
0!
b1000110 "
b1000110 $
#99
1!
b11000110 "
b11000110 $
#100
0!
b100110 "
b100110 $
#101
1!
b10100110 "
b10100110 $
#102
0!
b1100110 "
b1100110 $
#103
1!
b11100110 "
b11100110 $
#104
0!
b10110 "
b10110 $
#105
1!
b10010110 "
b10010110 $
#106
0!
b1010110 "
b1010110 $
#107
1!
b11010110 "
b11010110 $
#108
0!
b110110 "
b110110 $
#109
1!
b10110110 "
b10110110 $
#110
0!
b1110110 "
b1110110 $
#111
1!
b11110110 "
b11110110 $
#112
0!
b1110 "
b1110 $
#113
1!
b10001110 "
b10001110 $
#114
0!
b1001110 "
b1001110 $
#115
1!
b11001110 "
b11001110 $
#116
0!
b101110 "
b101110 $
#117
1!
b10101110 "
b10101110 $
#118
0!
b1101110 "
b1101110 $
#119
1!
b11101110 "
b11101110 $
#120
0!
b11110 "
b11110 $
#121
1!
b10011110 "
b10011110 $
#122
0!
b1011110 "
b1011110 $
#123
1!
b11011110 "
b11011110 $
#124
0!
b111110 "
b111110 $
#125
1!
b10111110 "
b10111110 $
#126
0!
b1111110 "
b1111110 $
#127
1!
b11111110 "
b11111110 $
#128
0!
b1 "
b1 $
#129
1!
b10000001 "
b10000001 $
#130
0!
b1000001 "
b1000001 $
#131
1!
b11000001 "
b11000001 $
#132
0!
b100001 "
b100001 $
#133
1!
b10100001 "
b10100001 $
#134
0!
b1100001 "
b1100001 $
#135
1!
b11100001 "
b11100001 $
#136
0!
b10001 "
b10001 $
#137
1!
b10010001 "
b10010001 $
#138
0!
b1010001 "
b1010001 $
#139
1!
b11010001 "
b11010001 $
#140
0!
b110001 "
b110001 $
#141
1!
b10110001 "
b10110001 $
#142
0!
b1110001 "
b1110001 $
#143
1!
b11110001 "
b11110001 $
#144
0!
b1001 "
b1001 $
#145
1!
b10001001 "
b10001001 $
#146
0!
b1001001 "
b1001001 $
#147
1!
b11001001 "
b11001001 $
#148
0!
b101001 "
b101001 $
#149
1!
b10101001 "
b10101001 $
#150
0!
b1101001 "
b1101001 $
#151
1!
b11101001 "
b11101001 $
#152
0!
b11001 "
b11001 $
#153
1!
b10011001 "
b10011001 $
#154
0!
b1011001 "
b1011001 $
#155
1!
b11011001 "
b11011001 $
#156
0!
b111001 "
b111001 $
#157
1!
b10111001 "
b10111001 $
#158
0!
b1111001 "
b1111001 $
#159
1!
b11111001 "
b11111001 $
#160
0!
b101 "
b101 $
#161
1!
b10000101 "
b10000101 $
#162
0!
b1000101 "
b1000101 $
#163
1!
b11000101 "
b11000101 $
#164
0!
b100101 "
b100101 $
#165
1!
b10100101 "
b10100101 $
#166
0!
b1100101 "
b1100101 $
#167
1!
b11100101 "
b11100101 $
#168
0!
b10101 "
b10101 $
#169
1!
b10010101 "
b10010101 $
#170
0!
b1010101 "
b1010101 $
#171
1!
b11010101 "
b11010101 $
#172
0!
b110101 "
b110101 $
#173
1!
b10110101 "
b10110101 $
#174
0!
b1110101 "
b1110101 $
#175
1!
b11110101 "
b11110101 $
#176
0!
b1101 "
b1101 $
#177
1!
b10001101 "
b10001101 $
#178
0!
b1001101 "
b1001101 $
#179
1!
b11001101 "
b11001101 $
#180
0!
b101101 "
b101101 $
#181
1!
b10101101 "
b10101101 $
#182
0!
b1101101 "
b1101101 $
#183
1!
b11101101 "
b11101101 $
#184
0!
b11101 "
b11101 $
#185
1!
b10011101 "
b10011101 $
#186
0!
b1011101 "
b1011101 $
#187
1!
b11011101 "
b11011101 $
#188
0!
b111101 "
b111101 $
#189
1!
b10111101 "
b10111101 $
#190
0!
b1111101 "
b1111101 $
#191
1!
b11111101 "
b11111101 $
#192
0!
b11 "
b11 $
#193
1!
b10000011 "
b10000011 $
#194
0!
b1000011 "
b1000011 $
#195
1!
b11000011 "
b11000011 $
#196
0!
b100011 "
b100011 $
#197
1!
b10100011 "
b10100011 $
#198
0!
b1100011 "
b1100011 $
#199
1!
b11100011 "
b11100011 $
#200
0!
b10011 "
b10011 $
#201
1!
b10010011 "
b10010011 $
#202
0!
b1010011 "
b1010011 $
#203
1!
b11010011 "
b11010011 $
#204
0!
b110011 "
b110011 $
#205
1!
b10110011 "
b10110011 $
#206
0!
b1110011 "
b1110011 $
#207
1!
b11110011 "
b11110011 $
#208
0!
b1011 "
b1011 $
#209
1!
b10001011 "
b10001011 $
#210
0!
b1001011 "
b1001011 $
#211
1!
b11001011 "
b11001011 $
#212
0!
b101011 "
b101011 $
#213
1!
b10101011 "
b10101011 $
#214
0!
b1101011 "
b1101011 $
#215
1!
b11101011 "
b11101011 $
#216
0!
b11011 "
b11011 $
#217
1!
b10011011 "
b10011011 $
#218
0!
b1011011 "
b1011011 $
#219
1!
b11011011 "
b11011011 $
#220
0!
b111011 "
b111011 $
#221
1!
b10111011 "
b10111011 $
#222
0!
b1111011 "
b1111011 $
#223
1!
b11111011 "
b11111011 $
#224
0!
b111 "
b111 $
#225
1!
b10000111 "
b10000111 $
#226
0!
b1000111 "
b1000111 $
#227
1!
b11000111 "
b11000111 $
#228
0!
b100111 "
b100111 $
#229
1!
b10100111 "
b10100111 $
#230
0!
b1100111 "
b1100111 $
#231
1!
b11100111 "
b11100111 $
#232
0!
b10111 "
b10111 $
#233
1!
b10010111 "
b10010111 $
#234
0!
b1010111 "
b1010111 $
#235
1!
b11010111 "
b11010111 $
#236
0!
b110111 "
b110111 $
#237
1!
b10110111 "
b10110111 $
#238
0!
b1110111 "
b1110111 $
#239
1!
b11110111 "
b11110111 $
#240
0!
b1111 "
b1111 $
#241
1!
b10001111 "
b10001111 $
#242
0!
b1001111 "
b1001111 $
#243
1!
b11001111 "
b11001111 $
#244
0!
b101111 "
b101111 $
#245
1!
b10101111 "
b10101111 $
#246
0!
b1101111 "
b1101111 $
#247
1!
b11101111 "
b11101111 $
#248
0!
b11111 "
b11111 $
#249
1!
b10011111 "
b10011111 $
#250
0!
b1011111 "
b1011111 $
#251
1!
b11011111 "
b11011111 $
#252
0!
b111111 "
b111111 $
#253
1!
b10111111 "
b10111111 $
#254
0!
b1111111 "
b1111111 $
#255
1!
b11111111 "
b11111111 $
#256
0!
b0 "
b0 $
b1 #
b1 %
#257
b10000000 "
b10000000 $
#258
1!
b1000000 "
b1000000 $
#259
b11000000 "
b11000000 $
#260
0!
b100000 "
b100000 $
#261
b10100000 "
b10100000 $
#262
1!
b1100000 "
b1100000 $
#263
b11100000 "
b11100000 $
#264
0!
b10000 "
b10000 $
#265
b10010000 "
b10010000 $
#266
1!
b1010000 "
b1010000 $
#267
b11010000 "
b11010000 $
#268
0!
b110000 "
b110000 $
#269
b10110000 "
b10110000 $
#270
1!
b1110000 "
b1110000 $
#271
b11110000 "
b11110000 $
#272
0!
b1000 "
b1000 $
#273
b10001000 "
b10001000 $
#274
1!
b1001000 "
b1001000 $
#275
b11001000 "
b11001000 $
#276
0!
b101000 "
b101000 $
#277
b10101000 "
b10101000 $
#278
1!
b1101000 "
b1101000 $
#279
b11101000 "
b11101000 $
#280
0!
b11000 "
b11000 $
#281
b10011000 "
b10011000 $
#282
1!
b1011000 "
b1011000 $
#283
b11011000 "
b11011000 $
#284
0!
b111000 "
b111000 $
#285
b10111000 "
b10111000 $
#286
1!
b1111000 "
b1111000 $
#287
b11111000 "
b11111000 $
#288
0!
b100 "
b100 $
#289
b10000100 "
b10000100 $
#290
1!
b1000100 "
b1000100 $
#291
b11000100 "
b11000100 $
#292
0!
b100100 "
b100100 $
#293
b10100100 "
b10100100 $
#294
1!
b1100100 "
b1100100 $
#295
b11100100 "
b11100100 $
#296
0!
b10100 "
b10100 $
#297
b10010100 "
b10010100 $
#298
1!
b1010100 "
b1010100 $
#299
b11010100 "
b11010100 $
#300
0!
b110100 "
b110100 $
#301
b10110100 "
b10110100 $
#302
1!
b1110100 "
b1110100 $
#303
b11110100 "
b11110100 $
#304
0!
b1100 "
b1100 $
#305
b10001100 "
b10001100 $
#306
1!
b1001100 "
b1001100 $
#307
b11001100 "
b11001100 $
#308
0!
b101100 "
b101100 $
#309
b10101100 "
b10101100 $
#310
1!
b1101100 "
b1101100 $
#311
b11101100 "
b11101100 $
#312
0!
b11100 "
b11100 $
#313
b10011100 "
b10011100 $
#314
1!
b1011100 "
b1011100 $
#315
b11011100 "
b11011100 $
#316
0!
b111100 "
b111100 $
#317
b10111100 "
b10111100 $
#318
1!
b1111100 "
b1111100 $
#319
b11111100 "
b11111100 $
#320
0!
b10 "
b10 $
#321
b10000010 "
b10000010 $
#322
1!
b1000010 "
b1000010 $
#323
b11000010 "
b11000010 $
#324
0!
b100010 "
b100010 $
#325
b10100010 "
b10100010 $
#326
1!
b1100010 "
b1100010 $
#327
b11100010 "
b11100010 $
#328
0!
b10010 "
b10010 $
#329
b10010010 "
b10010010 $
#330
1!
b1010010 "
b1010010 $
#331
b11010010 "
b11010010 $
#332
0!
b110010 "
b110010 $
#333
b10110010 "
b10110010 $
#334
1!
b1110010 "
b1110010 $
#335
b11110010 "
b11110010 $
#336
0!
b1010 "
b1010 $
#337
b10001010 "
b10001010 $
#338
1!
b1001010 "
b1001010 $
#339
b11001010 "
b11001010 $
#340
0!
b101010 "
b101010 $
#341
b10101010 "
b10101010 $
#342
1!
b1101010 "
b1101010 $
#343
b11101010 "
b11101010 $
#344
0!
b11010 "
b11010 $
#345
b10011010 "
b10011010 $
#346
1!
b1011010 "
b1011010 $
#347
b11011010 "
b11011010 $
#348
0!
b111010 "
b111010 $
#349
b10111010 "
b10111010 $
#350
1!
b1111010 "
b1111010 $
#351
b11111010 "
b11111010 $
#352
0!
b110 "
b110 $
#353
b10000110 "
b10000110 $
#354
1!
b1000110 "
b1000110 $
#355
b11000110 "
b11000110 $
#356
0!
b100110 "
b100110 $
#357
b10100110 "
b10100110 $
#358
1!
b1100110 "
b1100110 $
#359
b11100110 "
b11100110 $
#360
0!
b10110 "
b10110 $
#361
b10010110 "
b10010110 $
#362
1!
b1010110 "
b1010110 $
#363
b11010110 "
b11010110 $
#364
0!
b110110 "
b110110 $
#365
b10110110 "
b10110110 $
#366
1!
b1110110 "
b1110110 $
#367
b11110110 "
b11110110 $
#368
0!
b1110 "
b1110 $
#369
b10001110 "
b10001110 $
#370
1!
b1001110 "
b1001110 $
#371
b11001110 "
b11001110 $
#372
0!
b101110 "
b101110 $
#373
b10101110 "
b10101110 $
#374
1!
b1101110 "
b1101110 $
#375
b11101110 "
b11101110 $
#376
0!
b11110 "
b11110 $
#377
b10011110 "
b10011110 $
#378
1!
b1011110 "
b1011110 $
#379
b11011110 "
b11011110 $
#380
0!
b111110 "
b111110 $
#381
b10111110 "
b10111110 $
#382
1!
b1111110 "
b1111110 $
#383
b11111110 "
b11111110 $
#384
0!
b1 "
b1 $
#385
b10000001 "
b10000001 $
#386
1!
b1000001 "
b1000001 $
#387
b11000001 "
b11000001 $
#388
0!
b100001 "
b100001 $
#389
b10100001 "
b10100001 $
#390
1!
b1100001 "
b1100001 $
#391
b11100001 "
b11100001 $
#392
0!
b10001 "
b10001 $
#393
b10010001 "
b10010001 $
#394
1!
b1010001 "
b1010001 $
#395
b11010001 "
b11010001 $
#396
0!
b110001 "
b110001 $
#397
b10110001 "
b10110001 $
#398
1!
b1110001 "
b1110001 $
#399
b11110001 "
b11110001 $
#400
0!
b1001 "
b1001 $
#401
b10001001 "
b10001001 $
#402
1!
b1001001 "
b1001001 $
#403
b11001001 "
b11001001 $
#404
0!
b101001 "
b101001 $
#405
b10101001 "
b10101001 $
#406
1!
b1101001 "
b1101001 $
#407
b11101001 "
b11101001 $
#408
0!
b11001 "
b11001 $
#409
b10011001 "
b10011001 $
#410
1!
b1011001 "
b1011001 $
#411
b11011001 "
b11011001 $
#412
0!
b111001 "
b111001 $
#413
b10111001 "
b10111001 $
#414
1!
b1111001 "
b1111001 $
#415
b11111001 "
b11111001 $
#416
0!
b101 "
b101 $
#417
b10000101 "
b10000101 $
#418
1!
b1000101 "
b1000101 $
#419
b11000101 "
b11000101 $
#420
0!
b100101 "
b100101 $
#421
b10100101 "
b10100101 $
#422
1!
b1100101 "
b1100101 $
#423
b11100101 "
b11100101 $
#424
0!
b10101 "
b10101 $
#425
b10010101 "
b10010101 $
#426
1!
b1010101 "
b1010101 $
#427
b11010101 "
b11010101 $
#428
0!
b110101 "
b110101 $
#429
b10110101 "
b10110101 $
#430
1!
b1110101 "
b1110101 $
#431
b11110101 "
b11110101 $
#432
0!
b1101 "
b1101 $
#433
b10001101 "
b10001101 $
#434
1!
b1001101 "
b1001101 $
#435
b11001101 "
b11001101 $
#436
0!
b101101 "
b101101 $
#437
b10101101 "
b10101101 $
#438
1!
b1101101 "
b1101101 $
#439
b11101101 "
b11101101 $
#440
0!
b11101 "
b11101 $
#441
b10011101 "
b10011101 $
#442
1!
b1011101 "
b1011101 $
#443
b11011101 "
b11011101 $
#444
0!
b111101 "
b111101 $
#445
b10111101 "
b10111101 $
#446
1!
b1111101 "
b1111101 $
#447
b11111101 "
b11111101 $
#448
0!
b11 "
b11 $
#449
b10000011 "
b10000011 $
#450
1!
b1000011 "
b1000011 $
#451
b11000011 "
b11000011 $
#452
0!
b100011 "
b100011 $
#453
b10100011 "
b10100011 $
#454
1!
b1100011 "
b1100011 $
#455
b11100011 "
b11100011 $
#456
0!
b10011 "
b10011 $
#457
b10010011 "
b10010011 $
#458
1!
b1010011 "
b1010011 $
#459
b11010011 "
b11010011 $
#460
0!
b110011 "
b110011 $
#461
b10110011 "
b10110011 $
#462
1!
b1110011 "
b1110011 $
#463
b11110011 "
b11110011 $
#464
0!
b1011 "
b1011 $
#465
b10001011 "
b10001011 $
#466
1!
b1001011 "
b1001011 $
#467
b11001011 "
b11001011 $
#468
0!
b101011 "
b101011 $
#469
b10101011 "
b10101011 $
#470
1!
b1101011 "
b1101011 $
#471
b11101011 "
b11101011 $
#472
0!
b11011 "
b11011 $
#473
b10011011 "
b10011011 $
#474
1!
b1011011 "
b1011011 $
#475
b11011011 "
b11011011 $
#476
0!
b111011 "
b111011 $
#477
b10111011 "
b10111011 $
#478
1!
b1111011 "
b1111011 $
#479
b11111011 "
b11111011 $
#480
0!
b111 "
b111 $
#481
b10000111 "
b10000111 $
#482
1!
b1000111 "
b1000111 $
#483
b11000111 "
b11000111 $
#484
0!
b100111 "
b100111 $
#485
b10100111 "
b10100111 $
#486
1!
b1100111 "
b1100111 $
#487
b11100111 "
b11100111 $
#488
0!
b10111 "
b10111 $
#489
b10010111 "
b10010111 $
#490
1!
b1010111 "
b1010111 $
#491
b11010111 "
b11010111 $
#492
0!
b110111 "
b110111 $
#493
b10110111 "
b10110111 $
#494
1!
b1110111 "
b1110111 $
#495
b11110111 "
b11110111 $
#496
0!
b1111 "
b1111 $
#497
b10001111 "
b10001111 $
#498
1!
b1001111 "
b1001111 $
#499
b11001111 "
b11001111 $
#500
0!
b101111 "
b101111 $
#501
b10101111 "
b10101111 $
#502
1!
b1101111 "
b1101111 $
#503
b11101111 "
b11101111 $
#504
0!
b11111 "
b11111 $
#505
b10011111 "
b10011111 $
#506
1!
b1011111 "
b1011111 $
#507
b11011111 "
b11011111 $
#508
0!
b111111 "
b111111 $
#509
b10111111 "
b10111111 $
#510
1!
b1111111 "
b1111111 $
#511
b11111111 "
b11111111 $
#512
0!
b0 "
b0 $
b10 #
b10 %
#513
b10000000 "
b10000000 $
#514
b1000000 "
b1000000 $
#515
b11000000 "
b11000000 $
#516
1!
b100000 "
b100000 $
#517
b10100000 "
b10100000 $
#518
b1100000 "
b1100000 $
#519
b11100000 "
b11100000 $
#520
0!
b10000 "
b10000 $
#521
b10010000 "
b10010000 $
#522
b1010000 "
b1010000 $
#523
b11010000 "
b11010000 $
#524
1!
b110000 "
b110000 $
#525
b10110000 "
b10110000 $
#526
b1110000 "
b1110000 $
#527
b11110000 "
b11110000 $
#528
0!
b1000 "
b1000 $
#529
b10001000 "
b10001000 $
#530
b1001000 "
b1001000 $
#531
b11001000 "
b11001000 $
#532
1!
b101000 "
b101000 $
#533
b10101000 "
b10101000 $
#534
b1101000 "
b1101000 $
#535
b11101000 "
b11101000 $
#536
0!
b11000 "
b11000 $
#537
b10011000 "
b10011000 $
#538
b1011000 "
b1011000 $
#539
b11011000 "
b11011000 $
#540
1!
b111000 "
b111000 $
#541
b10111000 "
b10111000 $
#542
b1111000 "
b1111000 $
#543
b11111000 "
b11111000 $
#544
0!
b100 "
b100 $
#545
b10000100 "
b10000100 $
#546
b1000100 "
b1000100 $
#547
b11000100 "
b11000100 $
#548
1!
b100100 "
b100100 $
#549
b10100100 "
b10100100 $
#550
b1100100 "
b1100100 $
#551
b11100100 "
b11100100 $
#552
0!
b10100 "
b10100 $
#553
b10010100 "
b10010100 $
#554
b1010100 "
b1010100 $
#555
b11010100 "
b11010100 $
#556
1!
b110100 "
b110100 $
#557
b10110100 "
b10110100 $
#558
b1110100 "
b1110100 $
#559
b11110100 "
b11110100 $
#560
0!
b1100 "
b1100 $
#561
b10001100 "
b10001100 $
#562
b1001100 "
b1001100 $
#563
b11001100 "
b11001100 $
#564
1!
b101100 "
b101100 $
#565
b10101100 "
b10101100 $
#566
b1101100 "
b1101100 $
#567
b11101100 "
b11101100 $
#568
0!
b11100 "
b11100 $
#569
b10011100 "
b10011100 $
#570
b1011100 "
b1011100 $
#571
b11011100 "
b11011100 $
#572
1!
b111100 "
b111100 $
#573
b10111100 "
b10111100 $
#574
b1111100 "
b1111100 $
#575
b11111100 "
b11111100 $
#576
0!
b10 "
b10 $
#577
b10000010 "
b10000010 $
#578
b1000010 "
b1000010 $
#579
b11000010 "
b11000010 $
#580
1!
b100010 "
b100010 $
#581
b10100010 "
b10100010 $
#582
b1100010 "
b1100010 $
#583
b11100010 "
b11100010 $
#584
0!
b10010 "
b10010 $
#585
b10010010 "
b10010010 $
#586
b1010010 "
b1010010 $
#587
b11010010 "
b11010010 $
#588
1!
b110010 "
b110010 $
#589
b10110010 "
b10110010 $
#590
b1110010 "
b1110010 $
#591
b11110010 "
b11110010 $
#592
0!
b1010 "
b1010 $
#593
b10001010 "
b10001010 $
#594
b1001010 "
b1001010 $
#595
b11001010 "
b11001010 $
#596
1!
b101010 "
b101010 $
#597
b10101010 "
b10101010 $
#598
b1101010 "
b1101010 $
#599
b11101010 "
b11101010 $
#600
0!
b11010 "
b11010 $
#601
b10011010 "
b10011010 $
#602
b1011010 "
b1011010 $
#603
b11011010 "
b11011010 $
#604
1!
b111010 "
b111010 $
#605
b10111010 "
b10111010 $
#606
b1111010 "
b1111010 $
#607
b11111010 "
b11111010 $
#608
0!
b110 "
b110 $
#609
b10000110 "
b10000110 $
#610
b1000110 "
b1000110 $
#611
b11000110 "
b11000110 $
#612
1!
b100110 "
b100110 $
#613
b10100110 "
b10100110 $
#614
b1100110 "
b1100110 $
#615
b11100110 "
b11100110 $
#616
0!
b10110 "
b10110 $
#617
b10010110 "
b10010110 $
#618
b1010110 "
b1010110 $
#619
b11010110 "
b11010110 $
#620
1!
b110110 "
b110110 $
#621
b10110110 "
b10110110 $
#622
b1110110 "
b1110110 $
#623
b11110110 "
b11110110 $
#624
0!
b1110 "
b1110 $
#625
b10001110 "
b10001110 $
#626
b1001110 "
b1001110 $
#627
b11001110 "
b11001110 $
#628
1!
b101110 "
b101110 $
#629
b10101110 "
b10101110 $
#630
b1101110 "
b1101110 $
#631
b11101110 "
b11101110 $
#632
0!
b11110 "
b11110 $
#633
b10011110 "
b10011110 $
#634
b1011110 "
b1011110 $
#635
b11011110 "
b11011110 $
#636
1!
b111110 "
b111110 $
#637
b10111110 "
b10111110 $
#638
b1111110 "
b1111110 $
#639
b11111110 "
b11111110 $
#640
0!
b1 "
b1 $
#641
b10000001 "
b10000001 $
#642
b1000001 "
b1000001 $
#643
b11000001 "
b11000001 $
#644
1!
b100001 "
b100001 $
#645
b10100001 "
b10100001 $
#646
b1100001 "
b1100001 $
#647
b11100001 "
b11100001 $
#648
0!
b10001 "
b10001 $
#649
b10010001 "
b10010001 $
#650
b1010001 "
b1010001 $
#651
b11010001 "
b11010001 $
#652
1!
b110001 "
b110001 $
#653
b10110001 "
b10110001 $
#654
b1110001 "
b1110001 $
#655
b11110001 "
b11110001 $
#656
0!
b1001 "
b1001 $
#657
b10001001 "
b10001001 $
#658
b1001001 "
b1001001 $
#659
b11001001 "
b11001001 $
#660
1!
b101001 "
b101001 $
#661
b10101001 "
b10101001 $
#662
b1101001 "
b1101001 $
#663
b11101001 "
b11101001 $
#664
0!
b11001 "
b11001 $
#665
b10011001 "
b10011001 $
#666
b1011001 "
b1011001 $
#667
b11011001 "
b11011001 $
#668
1!
b111001 "
b111001 $
#669
b10111001 "
b10111001 $
#670
b1111001 "
b1111001 $
#671
b11111001 "
b11111001 $
#672
0!
b101 "
b101 $
#673
b10000101 "
b10000101 $
#674
b1000101 "
b1000101 $
#675
b11000101 "
b11000101 $
#676
1!
b100101 "
b100101 $
#677
b10100101 "
b10100101 $
#678
b1100101 "
b1100101 $
#679
b11100101 "
b11100101 $
#680
0!
b10101 "
b10101 $
#681
b10010101 "
b10010101 $
#682
b1010101 "
b1010101 $
#683
b11010101 "
b11010101 $
#684
1!
b110101 "
b110101 $
#685
b10110101 "
b10110101 $
#686
b1110101 "
b1110101 $
#687
b11110101 "
b11110101 $
#688
0!
b1101 "
b1101 $
#689
b10001101 "
b10001101 $
#690
b1001101 "
b1001101 $
#691
b11001101 "
b11001101 $
#692
1!
b101101 "
b101101 $
#693
b10101101 "
b10101101 $
#694
b1101101 "
b1101101 $
#695
b11101101 "
b11101101 $
#696
0!
b11101 "
b11101 $
#697
b10011101 "
b10011101 $
#698
b1011101 "
b1011101 $
#699
b11011101 "
b11011101 $
#700
1!
b111101 "
b111101 $
#701
b10111101 "
b10111101 $
#702
b1111101 "
b1111101 $
#703
b11111101 "
b11111101 $
#704
0!
b11 "
b11 $
#705
b10000011 "
b10000011 $
#706
b1000011 "
b1000011 $
#707
b11000011 "
b11000011 $
#708
1!
b100011 "
b100011 $
#709
b10100011 "
b10100011 $
#710
b1100011 "
b1100011 $
#711
b11100011 "
b11100011 $
#712
0!
b10011 "
b10011 $
#713
b10010011 "
b10010011 $
#714
b1010011 "
b1010011 $
#715
b11010011 "
b11010011 $
#716
1!
b110011 "
b110011 $
#717
b10110011 "
b10110011 $
#718
b1110011 "
b1110011 $
#719
b11110011 "
b11110011 $
#720
0!
b1011 "
b1011 $
#721
b10001011 "
b10001011 $
#722
b1001011 "
b1001011 $
#723
b11001011 "
b11001011 $
#724
1!
b101011 "
b101011 $
#725
b10101011 "
b10101011 $
#726
b1101011 "
b1101011 $
#727
b11101011 "
b11101011 $
#728
0!
b11011 "
b11011 $
#729
b10011011 "
b10011011 $
#730
b1011011 "
b1011011 $
#731
b11011011 "
b11011011 $
#732
1!
b111011 "
b111011 $
#733
b10111011 "
b10111011 $
#734
b1111011 "
b1111011 $
#735
b11111011 "
b11111011 $
#736
0!
b111 "
b111 $
#737
b10000111 "
b10000111 $
#738
b1000111 "
b1000111 $
#739
b11000111 "
b11000111 $
#740
1!
b100111 "
b100111 $
#741
b10100111 "
b10100111 $
#742
b1100111 "
b1100111 $
#743
b11100111 "
b11100111 $
#744
0!
b10111 "
b10111 $
#745
b10010111 "
b10010111 $
#746
b1010111 "
b1010111 $
#747
b11010111 "
b11010111 $
#748
1!
b110111 "
b110111 $
#749
b10110111 "
b10110111 $
#750
b1110111 "
b1110111 $
#751
b11110111 "
b11110111 $
#752
0!
b1111 "
b1111 $
#753
b10001111 "
b10001111 $
#754
b1001111 "
b1001111 $
#755
b11001111 "
b11001111 $
#756
1!
b101111 "
b101111 $
#757
b10101111 "
b10101111 $
#758
b1101111 "
b1101111 $
#759
b11101111 "
b11101111 $
#760
0!
b11111 "
b11111 $
#761
b10011111 "
b10011111 $
#762
b1011111 "
b1011111 $
#763
b11011111 "
b11011111 $
#764
1!
b111111 "
b111111 $
#765
b10111111 "
b10111111 $
