Verilog/example/dff/dff.v
module dff(q, d, clk, rst);
	input d, clk, rst;
	output reg q;
	
	always @ (posedge clk or negedge rst) begin
		if(!rst)
			q <= 0;
		else
			q <= d;
	end
	
endmodule

Verilog/example/dff/dff_tb.v
module dff_tb;
	reg d, clk, rst;
	wire q;
	
	dff uut(
		.q(q),
		.d(d),
		.clk(clk),
		.rst(rst)
	);
	
	initial begin
	$dumpfile("dump.vcd");
	$dumpvars(1, dff_tb);
		d = 0; clk = 0; rst = 0;
	#15	d <= 1;
	#10 rst <= 1;
	#20 d <= 0;
	#30 d <= 1;
	#40 $finish;
	end
	
	always #2 clk = ~clk;
endmodule

Verilog/HDL/dff/dump.vcd
$date
	Thu Feb 23 09:22:32 2023
$end
$version
	Icarus Verilog
$end
$timescale
	1s
$end
$scope module dff_tb $end
$var wire 1 ! q $end
$var reg 1 " clk $end
$var reg 1 # d $end
$var reg 1 $ rst $end
$upscope $end
$enddefinitions $end
#0
$dumpvars
0$
0#
0"
0!
$end
#2
1"
#4
0"
#6
1"
#8
0"
#10
1"
#12
0"
#14
1"
#15
1#
#16
0"
#18
1"
#20
0"
#22
1"
#24
0"
#25
1$
#26
1!
1"
#28
0"
#30
1"
#32
0"
#34
1"
#36
0"
#38
1"
#40
0"
#42
1"
#44
0"
#45
0#
#46
0!
1"
#48
0"
#50
1"
#52
0"
#54
1"
#56
0"
#58
1"
#60
0"
#62
1"
#64
0"
#66
1"
#68
0"
#70
1"
#72
0"
#74
1"
#75
1#
#76
0"
#78
1!
1"
