Verilog/example/nbits_shift_register/nshift.v
module nshift(out, d, dir, clk, rst, en);
	parameter N = 4;
	input d, clk, rst, en, dir;
	output reg[N-1:0] out;
	
	always @ (posedge clk) begin
		if(!rst)
			out <= 0;
		else begin
			if(en)
				case(dir)
					0: out <= {out[N-2:0], d};
					1: out <= {d, out[N-1:1]};
				endcase
			else 
				out <= out;
		end
	end
	
endmodule

Verilog/HDL/nbits_shift_register/nshift_tb.v
module nshift_tb;
	parameter N = 4;
	reg d, clk, rst, en, dir;
	wire [N-1:0] out;
	
	nshift uut(
		.out(out),
		.d(d),
		.clk(clk),
		.rst(rst),
		.en(en),
		.dir(dir)
	);
	
	initial begin
	$dumpfile("dump.vcd");
	$dumpvars(1, nshift_tb);
		rst = 0; clk = 0; en = 0; dir = 0;
	#10 rst = 1;
	#15 en = 1; d = 1;
	#20 dir = 1; d = 1;
	#25 en = 0;
	
	#500 $finish; 
	
	
	end
	
	always #2 clk = ~clk;

endmodule

Verilog/HDL/nbits_shift_register/dump.vcd
$date
	Thu Feb 23 12:09:16 2023
$end
$version
	Icarus Verilog
$end
$timescale
	1s
$end
$scope module nshift_tb $end
$var wire 4 ! out [3:0] $end
$var reg 1 " clk $end
$var reg 1 # d $end
$var reg 1 $ dir $end
$var reg 1 % en $end
$var reg 1 & rst $end
$upscope $end
$enddefinitions $end
#0
$dumpvars
0&
0%
0$
x#
0"
bx !
$end
#2
b0 !
1"
#4
0"
#6
1"
#8
0"
#10
1"
1&
#12
0"
#14
1"
#16
0"
#18
1"
#20
0"
#22
1"
#24
0"
#25
1#
1%
#26
b1 !
1"
#28
0"
#30
b11 !
1"
#32
0"
#34
b111 !
1"
#36
0"
#38
b1111 !
1"
#40
0"
#42
1"
#44
0"
#45
1$
#46
1"
#48
0"
#50
1"
#52
0"
#54
1"
#56
0"
#58
1"
#60
0"
#62
1"
#64
0"
#66
1"
#68
0"
#70
1"
0%
