Verilog/extra/mux3/mux21.v
module mux21(y, sel, i1, i0);
		output reg y;
		input sel, i1, i0;
		
		always @ (sel, i1, i0)
				if(sel)
					y <= i1;
				else 
					y <= i0;
endmodule

Verilog/mux3/mux21_tb.v
module mux21_tb;
		reg sel, i1, i0;
		wire y;
		
		mux21 inst (
				.sel(sel),
				.y(y),
				.i1(i1),
				.i0(i0)
		);
		
		initial begin
		$dumpfile("test_mux21.vcd");
		$dumpvars(0, mux21_tb);
				sel=0; i1=0; i0=0;
		#80	$finish;
		end
		
		always #10 i0 = ~i0;
		always #20 i1 = ~i1;
		always #40 sel = ~sel;
		
endmodule

Verilog/HDL/Mux/test_mux21.vcd
$date
	Mon Nov  7 12:12:45 2022
$end
$version
	Icarus Verilog
$end
$timescale
	1s
$end
$scope module mux21_tb $end
$var wire 1 ! y $end
$var reg 1 " i0 $end
$var reg 1 # i1 $end
$var reg 1 $ sel $end
$scope module inst $end
$var wire 1 " i0 $end
$var wire 1 # i1 $end
$var wire 1 $ sel $end
$var reg 1 ! y $end
$upscope $end
$upscope $end
$enddefinitions $end
#0
$dumpvars
0$
0#
0"
0!
$end
#10
1!
1"
#20
0!
0"
1#
#30
1!
1"
#40
0!
0"
0#
1$
#50
1"
#60
1!
0"
1#
#70
1"
#80
0!
0"
0#
0$
