Verilog/extra/mux3/mux21.v
module mux21(y, sel, i1, i0);
		output reg y;
		input sel, i1, i0;
		
		always @ (sel, i1, i0)
				if(sel)
					y <= i1;
				else 
					y <= i0;
endmodule

Verilog/HDL/Mux/mux41.v
`include "mux21.v"
module mux41(y, s0, s1, i0, i1, i2, i3);
		output y;
		input s0, s1, i0, i1, i2, i3;
		
		mux21 m1 (w3, s0, i1, i0);
		mux21 m2 (w4, s0, i3, i2);
		mux21 m3 (y, s1, w4, w3);
		
endmodule

Verilog/HDL/Mux/mux81.v
`include "mux41.v"

module mux81(y, s0, s1, s2, i0, i1, i2, i3, i4, i5, i6, i7);
				output y;
//				input [7:0] i;
//				input [2:0] s;

				input i0, i1, i2, i3, i4, i5, i6, i7;
				input s0, s1, s2;
				
				mux41 m1 (w3, s0, s1, i0, i1, i2, i3);
				mux41 m2 (w4, s0, s1, i4, i5, i6, i7);
				mux21 m3 (y, s2, w4, w3);
endmodule

Verilog/extra/mux/mux81_tb.v
module mux81_tb;
		reg s0, s1, s2, i0, i1, i2, i3, i4, i5, i6, i7;
		wire y;
		
		
		mux81 inst (
				.s0(s0),
				.s1(s1),
				.s2(s2),
				.y(y),
				.i0(i0),
				.i1(i1),
				.i2(i2),
				.i3(i3),
				.i4(i4),
				.i5(i5),
				.i6(i6),
				.i7(i7)
		);
		
		initial begin
		$dumpfile("test_mux81.vcd");
		$dumpvars(0, mux81_tb);
					s0 = 0; s1 = 0; s2 = 0; i0 = 0; i1 = 0; i2 = 0; i3 = 0; i4 = 0; i5 = 0; i6 = 0; i7 = 0;
		#2048	$finish;
		end
		
		always #1 i0 = ~i0;
		always #2 i1 = ~i1;
		always #4 i2 = ~i2;
		always #8 i3 = ~i3;
		always #16 i4= ~i4;
		always #32 i5 = ~i5;
		always #64 i6 = ~i6;
		always #128 i7 = ~i7;
		always #256 s0 = ~s0;
		always #512 s1 = ~s1;
		always #1024 s2 = ~s2;
		
endmodule

Verilog/extra/mux/test_mux81.vcd
$date
	Tue Nov  8 17:50:32 2022
$end
$version
	Icarus Verilog
$end
$timescale
	1s
$end
$scope module mux81_tb $end
$var wire 1 ! y $end
$var reg 1 " i0 $end
$var reg 1 # i1 $end
$var reg 1 $ i2 $end
$var reg 1 % i3 $end
$var reg 1 & i4 $end
$var reg 1 ' i5 $end
$var reg 1 ( i6 $end
$var reg 1 ) i7 $end
$var reg 1 * s0 $end
$var reg 1 + s1 $end
$var reg 1 , s2 $end
$scope module inst $end
$var wire 1 " i0 $end
$var wire 1 # i1 $end
$var wire 1 $ i2 $end
$var wire 1 % i3 $end
$var wire 1 & i4 $end
$var wire 1 ' i5 $end
$var wire 1 ( i6 $end
$var wire 1 ) i7 $end
$var wire 1 * s0 $end
$var wire 1 + s1 $end
$var wire 1 , s2 $end
$var wire 1 ! y $end
$var wire 1 - w4 $end
$var wire 1 . w3 $end
$scope module m1 $end
$var wire 1 " i0 $end
$var wire 1 # i1 $end
$var wire 1 $ i2 $end
$var wire 1 % i3 $end
$var wire 1 * s0 $end
$var wire 1 + s1 $end
$var wire 1 . y $end
$var wire 1 / w4 $end
$var wire 1 0 w3 $end
$scope module m1 $end
$var wire 1 " i0 $end
$var wire 1 # i1 $end
$var wire 1 * sel $end
$var reg 1 0 y $end
$upscope $end
$scope module m2 $end
$var wire 1 $ i0 $end
$var wire 1 % i1 $end
$var wire 1 * sel $end
$var reg 1 / y $end
$upscope $end
$scope module m3 $end
$var wire 1 0 i0 $end
$var wire 1 / i1 $end
$var wire 1 + sel $end
$var reg 1 . y $end
$upscope $end
$upscope $end
$scope module m2 $end
$var wire 1 & i0 $end
$var wire 1 ' i1 $end
$var wire 1 ( i2 $end
$var wire 1 ) i3 $end
$var wire 1 * s0 $end
$var wire 1 + s1 $end
$var wire 1 - y $end
$var wire 1 1 w4 $end
$var wire 1 2 w3 $end
$scope module m1 $end
$var wire 1 & i0 $end
$var wire 1 ' i1 $end
$var wire 1 * sel $end
$var reg 1 2 y $end
$upscope $end
$scope module m2 $end
$var wire 1 ( i0 $end
$var wire 1 ) i1 $end
$var wire 1 * sel $end
$var reg 1 1 y $end
$upscope $end
$scope module m3 $end
$var wire 1 2 i0 $end
$var wire 1 1 i1 $end
$var wire 1 + sel $end
$var reg 1 - y $end
$upscope $end
$upscope $end
$scope module m3 $end
$var wire 1 . i0 $end
$var wire 1 - i1 $end
$var wire 1 , sel $end
$var reg 1 ! y $end
$upscope $end
$upscope $end
$upscope $end
$enddefinitions $end
#0
$dumpvars
02
01
00
0/
0.
0-
0,
0+
0*
0)
0(
0'
0&
0%
0$
0#
0"
0!
$end
#1
1!
1.
10
1"
#2
0!
0.
00
0"
1#
#3
1!
1.
10
1"
#4
0!
0.
00
1/
0"
0#
1$
#5
1!
1.
10
1"
#6
0!
0.
00
0"
1#
#7
1!
1.
10
1"
#8
0!
0.
00
0/
0"
0#
0$
1%
#9
1!
1.
10
1"
#10
0!
0.
00
0"
1#
#11
1!
1.
10
1"
#12
0!
0.
00
1/
0"
0#
1$
#13
1!
1.
10
1"
#14
0!
0.
00
0"
1#
#15
1!
1.
10
1"
#16
0!
0.
1-
00
0/
12
0"
0#
0$
0%
1&
#17
1!
1.
10
1"
#18
0!
0.
00
0"
1#
#19
1!
1.
10
1"
#20
0!
0.
00
1/
0"
0#
1$
#21
1!
1.
10
1"
#22
0!
0.
00
0"
1#
#23
1!
1.
10
1"
#24
0!
0.
00
0/
0"
0#
0$
1%
#25
1!
1.
10
1"
#26
0!
0.
00
0"
1#
#27
1!
1.
10
1"
#28
0!
0.
00
1/
0"
0#
1$
#29
1!
1.
10
1"
#30
0!
0.
00
0"
1#
#31
1!
1.
10
1"
#32
0!
0.
0-
00
0/
02
0"
0#
0$
0%
0&
1'
#33
1!
1.
10
1"
#34
0!
0.
00
0"
1#
#35
1!
1.
10
1"
#36
0!
0.
00
1/
0"
0#
1$
#37
1!
1.
10
1"
#38
0!
0.
00
0"
1#
#39
1!
1.
10
1"
#40
0!
0.
00
0/
0"
0#
0$
1%
#41
1!
1.
10
1"
#42
0!
0.
00
0"
1#
#43
1!
1.
10
1"
#44
0!
0.
00
1/
0"
0#
1$
#45
1!
1.
10
1"
#46
0!
0.
00
0"
1#
#47
1!
1.
10
1"
#48
0!
0.
1-
00
0/
12
0"
0#
0$
0%
1&
#49
1!
1.
10
1"
#50
0!
0.
00
0"
1#
#51
1!
1.
10
1"
#52
0!
0.
00
1/
0"
0#
1$
#53
1!
1.
10
1"
#54
0!
0.
00
0"
1#
#55
1!
1.
10
1"
#56
0!
0.
00
0/
0"
0#
0$
1%
#57
1!
1.
10
1"
#58
0!
0.
00
0"
1#
#59
1!
1.
10
1"
#60
0!
0.
00
1/
0"
0#
1$
#61
1!
1.
10
1"
#62
0!
0.
00
0"
1#
#63
1!
1.
10
1"
#64
0!
0.
0-
00
0/
02
11
0"
0#
0$
0%
0&
0'
1(
#65
1!
1.
10
1"
#66
0!
0.
00
0"
1#
#67
1!
1.
10
1"
#68
0!
0.
00
1/
0"
0#
1$
#69
1!
1.
10
1"
#70
0!
0.
00
0"
1#
#71
1!
1.
10
1"
#72
0!
0.
00
0/
0"
0#
0$
1%
#73
1!
1.
10
1"
#74
0!
0.
00
0"
1#
#75
1!
1.
10
1"
#76
0!
0.
00
1/
0"
0#
1$
#77
1!
1.
10
1"
#78
0!
0.
00
0"
1#
#79
1!
1.
10
1"
#80
0!
0.
1-
00
0/
12
0"
0#
0$
0%
1&
#81
1!
1.
10
1"
#82
0!
0.
00
0"
1#
#83
1!
1.
10
1"
#84
0!
0.
00
1/
0"
0#
1$
#85
1!
1.
10
1"
#86
0!
0.
00
0"
1#
#87
1!
1.
10
1"
#88
0!
0.
00
0/
0"
0#
0$
1%
#89
1!
1.
10
1"
#90
0!
0.
00
0"
1#
#91
1!
1.
10
1"
#92
0!
0.
00
1/
0"
0#
1$
#93
1!
1.
10
1"
#94
0!
0.
00
0"
1#
#95
1!
1.
10
1"
#96
0!
0.
0-
00
0/
02
0"
0#
0$
0%
0&
1'
#97
1!
1.
10
1"
#98
0!
0.
00
0"
1#
#99
1!
1.
10
1"
#100
0!
0.
00
1/
0"
0#
1$
#101
1!
1.
10
1"
#102
0!
0.
00
0"
1#
#103
1!
1.
10
1"
#104
0!
0.
00
0/
0"
0#
0$
1%
#105
1!
1.
10
1"
#106
0!
0.
00
0"
1#
#107
1!
1.
10
1"
#108
0!
0.
00
1/
0"
0#
1$
#109
1!
1.
10
1"
#110
0!
0.
00
0"
1#
#111
1!
1.
10
1"
#112
0!
0.
1-
00
0/
12
0"
0#
0$
0%
1&
#113
1!
1.
10
1"
#114
0!
0.
00
0"
1#
#115
1!
1.
10
1"
#116
0!
0.
00
1/
0"
0#
1$
#117
1!
1.
10
1"
#118
0!
0.
00
0"
1#
#119
1!
1.
10
1"
#120
0!
0.
00
0/
0"
0#
0$
1%
#121
1!
1.
10
1"
#122
0!
0.
00
0"
1#
#123
1!
1.
10
1"
#124
0!
0.
00
1/
0"
0#
1$
#125
1!
1.
10
1"
#126
0!
0.
00
0"
1#
#127
1!
1.
10
1"
#128
0!
0.
0-
00
0/
02
01
0"
0#
0$
0%
0&
0'
0(
1)
#129
1!
1.
10
1"
#130
0!
0.
00
0"
1#
#131
1!
1.
10
1"
#132
0!
0.
00
1/
0"
0#
1$
#133
1!
1.
10
1"
#134
0!
0.
00
0"
1#
#135
1!
1.
10
1"
#136
0!
0.
00
0/
0"
0#
0$
1%
#137
1!
1.
10
1"
#138
0!
0.
00
0"
1#
#139
1!
1.
10
1"
#140
0!
0.
00
1/
0"
0#
1$
#141
1!
1.
10
1"
#142
0!
0.
00
0"
1#
#143
1!
1.
10
1"
#144
0!
0.
1-
00
0/
12
0"
0#
0$
0%
1&
#145
1!
1.
10
1"
#146
0!
0.
00
0"
1#
#147
1!
1.
10
1"
#148
0!
0.
00
1/
0"
0#
1$
#149
1!
1.
10
1"
#150
0!
0.
00
0"
1#
#151
1!
1.
10
1"
#152
0!
0.
00
0/
0"
0#
0$
1%
#153
1!
1.
10
1"
#154
0!
0.
00
0"
1#
#155
1!
1.
10
1"
#156
0!
0.
00
1/
0"
0#
1$
#157
1!
1.
10
1"
#158
0!
0.
00
0"
1#
#159
1!
1.
10
1"
#160
0!
0.
0-
00
0/
02
0"
0#
0$
0%
0&
1'
#161
1!
1.
10
1"
#162
0!
0.
00
0"
1#
#163
1!
1.
10
1"
#164
0!
0.
00
1/
0"
0#
1$
#165
1!
1.
10
1"
#166
0!
0.
00
0"
1#
#167
1!
1.
10
1"
#168
0!
0.
00
0/
0"
0#
0$
1%
#169
1!
1.
10
1"
#170
0!
0.
00
0"
1#
#171
1!
1.
10
1"
#172
0!
0.
00
1/
0"
0#
1$
#173
1!
1.
10
1"
#174
0!
0.
00
0"
1#
#175
1!
1.
10
1"
#176
0!
0.
1-
00
0/
12
0"
0#
0$
0%
1&
#177
1!
1.
10
1"
#178
0!
0.
00
0"
1#
#179
1!
1.
10
1"
#180
0!
0.
00
1/
0"
0#
1$
#181
1!
1.
10
1"
#182
0!
0.
00
0"
1#
#183
1!
1.
10
1"
#184
0!
0.
00
0/
0"
0#
0$
1%
#185
1!
1.
10
1"
#186
0!
0.
00
0"
1#
#187
1!
1.
10
1"
#188
0!
0.
00
1/
0"
0#
1$
#189
1!
1.
10
1"
#190
0!
0.
00
0"
1#
#191
1!
1.
10
1"
#192
0!
0.
0-
00
0/
02
11
0"
0#
0$
0%
0&
0'
1(
#193
1!
1.
10
1"
#194
0!
0.
00
0"
1#
#195
1!
1.
10
1"
#196
0!
0.
00
1/
0"
0#
1$
#197
1!
1.
10
1"
#198
0!
0.
00
0"
1#
#199
1!
1.
10
1"
#200
0!
0.
00
0/
0"
0#
0$
1%
#201
1!
1.
10
1"
#202
0!
0.
00
0"
1#
#203
1!
1.
10
1"
#204
0!
0.
00
1/
0"
0#
1$
#205
1!
1.
10
1"
#206
0!
0.
00
0"
1#
#207
1!
1.
10
1"
#208
0!
0.
1-
00
0/
12
0"
0#
0$
0%
1&
#209
1!
1.
10
1"
#210
0!
0.
00
0"
1#
#211
1!
1.
10
1"
#212
0!
0.
00
1/
0"
0#
1$
#213
1!
1.
10
1"
#214
0!
0.
00
0"
1#
#215
1!
1.
10
1"
#216
0!
0.
00
0/
0"
0#
0$
1%
#217
1!
1.
10
1"
#218
0!
0.
00
0"
1#
#219
1!
1.
10
1"
#220
0!
0.
00
1/
0"
0#
1$
#221
1!
1.
10
1"
#222
0!
0.
00
0"
1#
#223
1!
1.
10
1"
#224
0!
0.
0-
00
0/
02
0"
0#
0$
0%
0&
1'
#225
1!
1.
10
1"
#226
0!
0.
00
0"
1#
#227
1!
1.
10
1"
#228
0!
0.
00
1/
0"
0#
1$
#229
1!
1.
10
1"
#230
0!
0.
00
0"
1#
#231
1!
1.
10
1"
#232
0!
0.
00
0/
0"
0#
0$
1%
#233
1!
1.
10
1"
#234
0!
0.
00
0"
1#
#235
1!
1.
10
1"
#236
0!
0.
00
1/
0"
0#
1$
#237
1!
1.
10
1"
#238
0!
0.
00
0"
1#
#239
1!
1.
10
1"
#240
0!
0.
1-
00
0/
12
0"
0#
0$
0%
1&
#241
1!
1.
10
1"
#242
0!
0.
00
0"
1#
#243
1!
1.
10
1"
#244
0!
0.
00
1/
0"
0#
1$
#245
1!
1.
10
1"
#246
0!
0.
00
0"
1#
#247
1!
1.
10
1"
#248
0!
0.
00
0/
0"
0#
0$
1%
#249
1!
1.
10
1"
#250
0!
0.
00
0"
1#
#251
1!
1.
10
1"
#252
0!
0.
00
1/
0"
0#
1$
#253
1!
1.
10
1"
#254
0!
0.
00
0"
1#
#255
1!
1.
10
1"
#256
0!
0.
0-
00
0/
02
01
0"
0#
0$
0%
0&
0'
0(
0)
1*
#257
1"
#258
1!
1.
10
0"
1#
#259
1"
#260
0!
0.
00
0"
0#
1$
#261
1"
#262
1!
1.
10
0"
1#
#263
1"
#264
0!
0.
00
1/
0"
0#
0$
1%
#265
1"
#266
1!
1.
10
0"
1#
#267
1"
#268
0!
0.
00
0"
0#
1$
#269
1"
#270
1!
1.
10
0"
1#
#271
1"
#272
0!
0.
00
0/
0"
0#
0$
0%
1&
#273
1"
#274
1!
1.
10
0"
1#
#275
1"
#276
0!
0.
00
0"
0#
1$
#277
1"
#278
1!
1.
10
0"
1#
#279
1"
#280
0!
0.
00
1/
0"
0#
0$
1%
#281
1"
#282
1!
1.
10
0"
1#
#283
1"
#284
0!
0.
00
0"
0#
1$
#285
1"
#286
1!
1.
10
0"
1#
#287
1"
#288
0!
0.
1-
00
0/
12
0"
0#
0$
0%
0&
1'
#289
1"
#290
1!
1.
10
0"
1#
#291
1"
#292
0!
0.
00
0"
0#
1$
#293
1"
#294
1!
1.
10
0"
1#
#295
1"
#296
0!
0.
00
1/
0"
0#
0$
1%
#297
1"
#298
1!
1.
10
0"
1#
#299
1"
#300
0!
0.
00
0"
0#
1$
#301
1"
#302
1!
1.
10
0"
1#
#303
1"
#304
0!
0.
00
0/
0"
0#
0$
0%
1&
#305
1"
#306
1!
1.
10
0"
1#
#307
1"
#308
0!
0.
00
0"
0#
1$
#309
1"
#310
1!
1.
10
0"
1#
#311
1"
#312
0!
0.
00
1/
0"
0#
0$
1%
#313
1"
#314
1!
1.
10
0"
1#
#315
1"
#316
0!
0.
00
0"
0#
1$
#317
1"
#318
1!
1.
10
0"
1#
#319
1"
#320
0!
0.
0-
00
0/
02
0"
0#
0$
0%
0&
0'
1(
#321
1"
#322
1!
1.
10
0"
1#
#323
1"
#324
0!
0.
00
0"
0#
1$
#325
1"
#326
1!
1.
10
0"
1#
#327
1"
#328
0!
0.
00
1/
0"
0#
0$
1%
#329
1"
#330
1!
1.
10
0"
1#
#331
1"
#332
0!
0.
00
0"
0#
1$
#333
1"
#334
1!
1.
10
0"
1#
#335
1"
#336
0!
0.
00
0/
0"
0#
0$
0%
1&
#337
1"
#338
1!
1.
10
0"
1#
#339
1"
#340
0!
0.
00
0"
0#
1$
#341
1"
#342
1!
1.
10
0"
1#
#343
1"
#344
0!
0.
00
1/
0"
0#
0$
1%
#345
1"
#346
1!
1.
10
0"
1#
#347
1"
#348
0!
0.
00
0"
0#
1$
#349
1"
#350
1!
1.
10
0"
1#
#351
1"
#352
0!
0.
1-
00
0/
12
0"
0#
0$
0%
0&
1'
#353
1"
#354
1!
1.
10
0"
1#
#355
1"
#356
0!
0.
00
0"
0#
1$
#357
1"
#358
1!
1.
10
0"
1#
#359
1"
#360
0!
0.
00
1/
0"
0#
0$
1%
#361
1"
#362
1!
1.
10
0"
1#
#363
1"
#364
0!
0.
00
0"
0#
1$
#365
1"
#366
1!
1.
10
0"
1#
#367
1"
#368
0!
0.
00
0/
0"
0#
0$
0%
1&
#369
1"
#370
1!
1.
10
0"
1#
#371
1"
#372
0!
0.
00
0"
0#
1$
#373
1"
#374
1!
1.
10
0"
1#
#375
1"
#376
0!
0.
00
1/
0"
0#
0$
1%
#377
1"
#378
1!
1.
10
0"
1#
#379
1"
#380
0!
0.
00
0"
0#
1$
#381
1"
#382
1!
1.
10
0"
1#
#383
1"
#384
0!
0.
0-
00
0/
02
11
0"
0#
0$
0%
0&
0'
0(
1)
#385
1"
#386
1!
1.
10
0"
1#
#387
1"
#388
0!
0.
00
0"
0#
1$
#389
1"
#390
1!
1.
10
0"
1#
#391
1"
#392
0!
0.
00
1/
0"
0#
0$
1%
#393
1"
#394
1!
1.
10
0"
1#
#395
1"
#396
0!
0.
00
0"
0#
1$
#397
1"
#398
1!
1.
10
0"
1#
#399
1"
#400
0!
0.
00
0/
0"
0#
0$
0%
1&
#401
1"
#402
1!
1.
10
0"
1#
#403
1"
#404
0!
0.
00
0"
0#
1$
#405
1"
#406
1!
1.
10
0"
1#
#407
1"
#408
0!
0.
00
1/
0"
0#
0$
1%
#409
1"
#410
1!
1.
10
0"
1#
#411
1"
#412
0!
0.
00
0"
0#
1$
#413
1"
#414
1!
1.
10
0"
1#
#415
1"
#416
0!
0.
1-
00
0/
12
0"
0#
0$
0%
0&
1'
#417
1"
#418
1!
1.
10
0"
1#
#419
1"
#420
0!
0.
00
0"
0#
1$
#421
1"
#422
1!
1.
10
0"
1#
#423
1"
#424
0!
0.
00
1/
0"
0#
0$
1%
#425
1"
#426
1!
1.
10
0"
1#
#427
1"
#428
0!
0.
00
0"
0#
1$
#429
1"
#430
1!
1.
10
0"
1#
#431
1"
#432
0!
0.
00
0/
0"
0#
0$
0%
1&
#433
1"
#434
1!
1.
10
0"
1#
#435
1"
#436
0!
0.
00
0"
0#
1$
#437
1"
#438
1!
1.
10
0"
1#
#439
1"
#440
0!
0.
00
1/
0"
0#
0$
1%
#441
1"
#442
1!
1.
10
0"
1#
#443
1"
#444
0!
0.
00
0"
0#
1$
#445
1"
#446
1!
1.
10
0"
1#
#447
1"
#448
0!
0.
0-
00
0/
02
0"
0#
0$
0%
0&
0'
1(
#449
1"
#450
1!
1.
10
0"
1#
#451
1"
#452
0!
0.
00
0"
0#
1$
#453
1"
#454
1!
1.
10
0"
1#
#455
1"
#456
0!
0.
00
1/
0"
0#
0$
1%
#457
1"
#458
1!
1.
10
0"
1#
#459
1"
#460
0!
0.
00
0"
0#
1$
#461
1"
#462
1!
1.
10
0"
1#
#463
1"
#464
0!
0.
00
0/
0"
0#
0$
0%
1&
#465
1"
#466
1!
1.
10
0"
1#
#467
1"
#468
0!
0.
00
0"
0#
1$
#469
1"
#470
1!
1.
10
0"
1#
#471
1"
#472
0!
0.
00
1/
0"
0#
0$
1%
#473
1"
#474
1!
1.
10
0"
1#
#475
1"
#476
0!
0.
00
0"
0#
1$
#477
1"
#478
1!
1.
10
0"
1#
#479
1"
#480
0!
0.
1-
00
0/
12
0"
0#
0$
0%
0&
1'
#481
1"
#482
1!
1.
10
0"
1#
#483
1"
#484
0!
0.
00
0"
0#
1$
#485
1"
#486
1!
1.
10
0"
1#
#487
1"
#488
0!
0.
00
1/
0"
0#
0$
1%
#489
1"
#490
1!
1.
10
0"
1#
#491
1"
#492
0!
0.
00
0"
0#
1$
#493
1"
#494
1!
1.
10
0"
1#
#495
1"
#496
0!
0.
00
0/
0"
0#
0$
0%
1&
#497
1"
#498
1!
1.
10
0"
1#
#499
1"
#500
0!
0.
00
0"
0#
1$
#501
1"
#502
1!
1.
10
0"
1#
#503
1"
#504
0!
0.
00
1/
0"
0#
0$
1%
#505
1"
#506
1!
1.
10
0"
1#
#507
1"
#508
0!
0.
00
0"
0#
1$
#509
1"
#510
1!
1.
10
0"
1#
#511
1"
#512
0!
0.
0-
00
0/
02
01
0"
0#
0$
0%
0&
0'
0(
0)
0*
1+
#513
10
1"
#514
00
0"
1#
#515
10
1"
#516
1!
1.
00
1/
0"
0#
1$
#517
10
1"
#518
00
0"
1#
#519
10
1"
#520
0!
0.
00
0/
0"
0#
0$
1%
#521
10
1"
#522
00
0"
1#
#523
10
1"
#524
1!
1.
00
1/
0"
0#
1$
#525
10
1"
#526
00
0"
1#
#527
10
1"
#528
0!
0.
00
0/
12
0"
0#
0$
0%
1&
#529
10
1"
#530
00
0"
1#
#531
10
1"
#532
1!
1.
00
1/
0"
0#
1$
#533
10
1"
#534
00
0"
1#
#535
10
1"
#536
0!
0.
00
0/
0"
0#
0$
1%
#537
10
1"
#538
00
0"
1#
#539
10
1"
#540
1!
1.
00
1/
0"
0#
1$
#541
10
1"
#542
00
0"
1#
#543
10
1"
#544
0!
0.
00
0/
02
0"
0#
0$
0%
0&
1'
#545
10
1"
#546
00
0"
1#
#547
10
1"
#548
1!
1.
00
1/
0"
0#
1$
#549
10
1"
#550
00
0"
1#
#551
10
1"
#552
0!
0.
00
0/
0"
0#
0$
1%
#553
10
1"
#554
00
0"
1#
#555
10
1"
#556
1!
1.
00
1/
0"
0#
1$
#557
10
1"
#558
00
0"
1#
#559
10
1"
#560
0!
0.
00
0/
12
0"
0#
0$
0%
1&
#561
10
1"
#562
00
0"
1#
#563
10
1"
#564
1!
1.
00
1/
0"
0#
1$
#565
10
1"
#566
00
0"
1#
#567
10
1"
#568
0!
0.
00
0/
0"
0#
0$
1%
#569
10
1"
#570
00
0"
1#
#571
10
1"
#572
1!
1.
00
1/
0"
0#
1$
#573
10
1"
#574
00
0"
1#
#575
10
1"
#576
0!
0.
1-
00
0/
02
11
0"
0#
0$
0%
0&
0'
1(
#577
10
1"
#578
00
0"
1#
#579
10
1"
#580
1!
1.
00
1/
0"
0#
1$
#581
10
1"
#582
00
0"
1#
#583
10
1"
#584
0!
0.
00
0/
0"
0#
0$
1%
#585
10
1"
#586
00
0"
1#
#587
10
1"
#588
1!
1.
00
1/
0"
0#
1$
#589
10
1"
#590
00
0"
1#
#591
10
1"
#592
0!
0.
00
0/
12
0"
0#
0$
0%
1&
#593
10
1"
#594
00
0"
1#
#595
10
1"
#596
1!
1.
00
1/
0"
0#
1$
#597
10
1"
#598
00
0"
1#
#599
10
1"
#600
0!
0.
00
0/
0"
0#
0$
1%
#601
10
1"
#602
00
0"
1#
#603
10
1"
#604
1!
1.
00
1/
0"
0#
1$
#605
10
1"
#606
00
0"
1#
#607
10
1"
#608
0!
0.
00
0/
02
0"
0#
0$
0%
0&
1'
#609
10
1"
#610
00
0"
1#
#611
10
1"
#612
1!
1.
00
1/
0"
0#
1$
#613
10
1"
#614
00
0"
1#
#615
10
1"
#616
0!
0.
00
0/
0"
0#
0$
1%
#617
10
1"
#618
00
0"
1#
#619
10
1"
#620
1!
1.
00
1/
0"
0#
1$
#621
10
1"
#622
00
0"
1#
#623
10
1"
#624
0!
0.
00
0/
12
0"
0#
0$
0%
1&
#625
10
1"
#626
00
0"
1#
#627
10
1"
#628
1!
1.
00
1/
0"
0#
1$
#629
10
1"
#630
00
0"
1#
#631
10
1"
#632
0!
0.
00
0/
0"
0#
0$
1%
#633
10
1"
#634
00
0"
1#
#635
10
1"
#636
1!
1.
00
1/
0"
0#
1$
#637
10
1"
#638
00
0"
1#
#639
10
1"
#640
0!
0.
0-
00
0/
02
01
0"
0#
0$
0%
0&
0'
0(
1)
#641
10
1"
#642
00
0"
1#
#643
10
1"
#644
1!
1.
00
1/
0"
0#
1$
#645
10
1"
#646
00
0"
1#
#647
10
1"
#648
0!
0.
00
0/
0"
0#
0$
1%
#649
10
1"
#650
00
0"
1#
#651
10
1"
#652
1!
1.
00
1/
0"
0#
1$
#653
10
1"
#654
00
0"
1#
#655
10
1"
#656
0!
0.
00
0/
12
0"
0#
0$
0%
1&
#657
10
1"
#658
00
0"
1#
#659
10
1"
#660
1!
1.
00
1/
0"
0#
1$
#661
10
1"
#662
00
0"
1#
#663
10
1"
#664
0!
0.
00
0/
0"
0#
0$
1%
#665
10
1"
#666
00
0"
1#
#667
10
1"
#668
1!
1.
00
1/
0"
0#
1$
#669
10
1"
#670
00
0"
1#
#671
10
1"
#672
0!
0.
00
0/
02
0"
0#
0$
0%
0&
1'
#673
10
1"
#674
00
0"
1#
#675
10
1"
#676
1!
1.
00
1/
0"
0#
1$
#677
10
1"
#678
00
0"
1#
#679
10
1"
#680
0!
0.
00
0/
0"
0#
0$
1%
#681
10
1"
#682
00
0"
1#
#683
10
1"
#684
1!
1.
00
1/
0"
0#
1$
#685
10
1"
#686
00
0"
1#
#687
10
1"
#688
0!
0.
00
0/
12
0"
0#
0$
0%
1&
#689
10
1"
#690
00
0"
1#
#691
10
1"
#692
1!
1.
00
1/
0"
0#
1$
#693
10
1"
#694
00
0"
1#
#695
10
1"
#696
0!
0.
00
0/
0"
0#
0$
1%
#697
10
1"
#698
00
0"
1#
#699
10
1"
#700
1!
1.
00
1/
0"
0#
1$
#701
10
1"
#702
00
0"
1#
#703
10
1"
#704
0!
0.
1-
00
0/
02
11
0"
0#
0$
0%
0&
0'
1(
#705
10
1"
#706
00
0"
1#
#707
10
1"
#708
1!
1.
00
1/
0"
0#
1$
#709
10
1"
#710
00
0"
1#
#711
10
1"
#712
0!
0.
00
0/
0"
0#
0$
1%
#713
10
1"
#714
00
0"
1#
#715
10
1"
#716
1!
1.
00
1/
0"
0#
1$
#717
10
1"
#718
00
0"
1#
#719
10
1"
#720
0!
0.
00
0/
12
0"
0#
0$
0%
1&
#721
10
1"
#722
00
0"
1#
#723
10
1"
#724
1!
1.
00
1/
0"
0#
1$
#725
10
1"
#726
00
0"
1#
#727
10
1"
#728
0!
0.
00
0/
0"
0#
0$
1%
#729
10
1"
#730
00
0"
1#
#731
10
1"
#732
1!
1.
00
1/
0"
0#
1$
#733
10
1"
#734
00
0"
1#
#735
10
1"
#736
0!
0.
00
0/
02
0"
0#
0$
0%
0&
1'
#737
10
1"
#738
00
0"
1#
#739
10
1"
#740
1!
1.
00
1/
0"
0#
1$
#741
10
1"
#742
00
0"
1#
#743
10
1"
#744
0!
0.
00
0/
0"
0#
0$
1%
#745
10
1"
#746
00
0"
1#
#747
10
1"
#748
1!
1.
00
1/
0"
0#
1$
#749
10
1"
#750
00
0"
1#
#751
10
1"
#752
0!
0.
00
0/
12
0"
0#
0$
0%
1&
#753
10
1"
#754
00
0"
1#
#755
10
1"
#756
1!
1.
00
1/
0"
0#
1$
#757
10
1"
#758
00
0"
1#
#759
10
1"
#760
0!
0.
00
0/
0"
0#
0$
1%
#761
10
1"
#762
00
0"
1#
#763
10
1"
#764
1!
1.
00
1/
0"
0#
1$
#765
10
1"
#766
00
0"
1#
#767
10
1"
#768
0!
0.
0-
00
0/
02
01
0"
0#
0$
0%
0&
0'
0(
0)
1*
#769
1"
#770
10
0"
1#
#771
1"
#772
00
0"
0#
1$
#773
1"
#774
10
0"
1#
#775
1"
#776
1!
1.
00
1/
0"
0#
0$
1%
#777
1"
#778
10
0"
1#
#779
1"
#780
00
0"
0#
1$
#781
1"
#782
10
0"
1#
#783
1"
#784
0!
0.
00
0/
0"
0#
0$
0%
1&
#785
1"
#786
10
0"
1#
#787
1"
#788
00
0"
0#
1$
#789
1"
#790
10
0"
1#
#791
1"
#792
1!
1.
00
1/
0"
0#
0$
1%
#793
1"
#794
10
0"
1#
#795
1"
#796
00
0"
0#
1$
#797
1"
#798
10
0"
1#
#799
1"
#800
0!
0.
00
0/
12
0"
0#
0$
0%
0&
1'
#801
1"
#802
10
0"
1#
#803
1"
#804
00
0"
0#
1$
#805
1"
#806
10
0"
1#
#807
1"
#808
1!
1.
00
1/
0"
0#
0$
1%
#809
1"
#810
10
0"
1#
#811
1"
#812
00
0"
0#
1$
#813
1"
#814
10
0"
1#
#815
1"
#816
0!
0.
00
0/
0"
0#
0$
0%
1&
#817
1"
#818
10
0"
1#
#819
1"
#820
00
0"
0#
1$
#821
1"
#822
10
0"
1#
#823
1"
#824
1!
1.
00
1/
0"
0#
0$
1%
#825
1"
#826
10
0"
1#
#827
1"
#828
00
0"
0#
1$
#829
1"
#830
10
0"
1#
#831
1"
#832
0!
0.
00
0/
02
0"
0#
0$
0%
0&
0'
1(
#833
1"
#834
10
0"
1#
#835
1"
#836
00
0"
0#
1$
#837
1"
#838
10
0"
1#
#839
1"
#840
1!
1.
00
1/
0"
0#
0$
1%
#841
1"
#842
10
0"
1#
#843
1"
#844
00
0"
0#
1$
#845
1"
#846
10
0"
1#
#847
1"
#848
0!
0.
00
0/
0"
0#
0$
0%
1&
#849
1"
#850
10
0"
1#
#851
1"
#852
00
0"
0#
1$
#853
1"
#854
10
0"
1#
#855
1"
#856
1!
1.
00
1/
0"
0#
0$
1%
#857
1"
#858
10
0"
1#
#859
1"
#860
00
0"
0#
1$
#861
1"
#862
10
0"
1#
#863
1"
#864
0!
0.
00
0/
12
0"
0#
0$
0%
0&
1'
#865
1"
#866
10
0"
1#
#867
1"
#868
00
0"
0#
1$
#869
1"
#870
10
0"
1#
#871
1"
