Verilog/adder/half_adder.v
module half_adder(s, c, a, b);
	output reg s, c;
	input a, b;


	always @ ( * )	
	begin
		s = a ^ b;
		c = a & b;
	end
endmodule

Verilog/adder/Onefull_adder.v
`include "half_adder.v"
module Onefull_adder(s, co, a, b, ci);
	input a, b, ci;
	output s, co;
	wire x, y;
	
	half_adder h1(x, c, a, b);
	half_adder h2(s, y, x, ci);
	or (co, y, c);
endmodule

Verilog/adder/Onefull_adder_tb.v
module Onefull_adder_tb;
	reg a; reg b; reg ci;
	wire s; wire co;
	
	Onefull_adder inst (
		.s(s),
		.co(co),
		.a(a),
		.b(b),
		.ci(ci)
	);

	initial begin
			$dumpfile("test_Onefull_adder.vcd");
			$dumpvars(0, Onefull_adder_tb);
			a = 0; b = 0; ci = 0;
	#40		$finish;
	end
	
	always #5 ci = ~ci;
	always #10 b = ~b;
	always #20 a = ~a;
endmodule

Verilog/adder/test_Onefull_adder.vcd
$date
	Wed Nov  9 00:11:15 2022
$end
$version
	Icarus Verilog
$end
$timescale
	1s
$end
$scope module Onefull_adder_tb $end
$var wire 1 ! s $end
$var wire 1 " co $end
$var reg 1 # a $end
$var reg 1 $ b $end
$var reg 1 % ci $end
$scope module inst $end
$var wire 1 # a $end
$var wire 1 $ b $end
$var wire 1 % ci $end
$var wire 1 " co $end
$var wire 1 & y $end
$var wire 1 ' x $end
$var wire 1 ! s $end
$var wire 1 ( c $end
$scope module h1 $end
$var wire 1 # a $end
$var wire 1 $ b $end
$var reg 1 ( c $end
$var reg 1 ' s $end
$upscope $end
$scope module h2 $end
$var wire 1 ' a $end
$var wire 1 % b $end
$var reg 1 & c $end
$var reg 1 ! s $end
$upscope $end
$upscope $end
$upscope $end
$enddefinitions $end
#0
$dumpvars
0(
0'
0&
0%
0$
0#
0"
0!
$end
#5
1!
1%
#10
1'
0%
1$
#15
1"
1&
0!
1%
#20
0"
0&
1!
0%
0$
1#
#25
1"
1&
0!
1%
#30
0&
1(
0'
0%
1$
#35
1!
1%
#40
0"
0!
0(
0%
0$
0#
